Workbook

Sheet LEEME
A1: Screening log — Deliverable 4 (Mini systematic review, PRISMA 2020)
A2: Tesis: Verifiable, human-in-the-loop generative AI for contractual clause recommendation (J. Inca Cárdenas)
A4: Hojas
A5: Search_Log: una fila por fuente. Las celdas amarillas las completa el investigador (fecha, string exacto, filtros, total mostrado).
A6: Registros: los 2,910 registros tal como se exportaron, con la columna duplicado_de (ID del registro conservado) y el criterio de deduplicación.
A7: Cribado: los 2,579 registros únicos con etapa, decisión, código y método. Columnas "Verificación" y "Acuerdo" para el control humano.
A8: Otros_metodos: Consensus, SSRN y estudios semilla del D3, cruzados contra las bases.
A9: PRISMA: conteos por casilla del diagrama, calculados con fórmulas a partir de las otras hojas.
A11: Decisiones de protocolo (confirmadas por el investigador)
A12: Conference papers revisados por pares: se incluyen.
A13: Preprints solo en arXiv (sin versión publicada): se excluyen (A1) y se reservan para snowballing.
A14: Consensus y estudios semilla del D3: se reportan en la columna "identificación por otros métodos".
... A47: Revisión humana: se usa la hoja Revision_150 (muestra estratificada de 150 registros, semilla 2026) en lugar de las 403 filas originales; la columna "muestra" de Cribado marca esos 150.

Sheet Revision_150
A1: Revisión humana de una muestra estratificada de 150 registros
A2: Lee título y abstract; responde en "¿De acuerdo?" Sí o No. Si es No, escribe la decisión correcta en Comentario. Criterio: IA generativa (LLM/RAG) + textos legales/contractuales/regulatorios + mide verificabilidad, alucinación o corrección legal.
A3: Revisadas | B3: Acuerdo (Sí) | C3: Desacuerdo (No) | D3: % de acuerdo
A4: =COUNTA(G6:G155) -> 150 | B4: =COUNTIF(G6:G155,"Sí") -> 0 | C4: =COUNTIF(G6:G155,"No") -> 119 | D4: =IFERROR(C4/A4,"") -> 0.79333333
A5: N.º | B5: rec_id | C5: Estrato | D5: Título | E5: Año | F5: Abstract (recortado) | G5: ¿De acuerdo? (Sí/No) | H5: Comentario / decisión correcta
A6: 1 | B6: R2749 | C6: Incluido | D6: A Hybrid Knowledge-Enhanced Legal AI System for Construction Contract Disputes | E6: 2026 | F6: With rapid urbanization and expanding infrastructure, construction contract disputes are increasing in volume and complexity, challenging traditional adjudication. This study proposes a domain-specific legal artificial intelligence (AI) system for construction contract disputes via hybrid knowledge integration based on the retrieval-augmented generation (RAG) paradigm, integrating five core legal texts and 500 adjudication cases within a dual-engine architecture. The knowledge base encodes legal concepts, relations, and rules to enable structured semantic inference. The DeepSeek-R1 reasoning engine analyzes case facts and legal logic via constrained generation, while the BGE-M3 retrieval module matches legal provisions and precedents using multivector indexing. A tripartite evaluation framework—semantic similarity, legal provision citation accuracy, and issue prediction F1 score—validates system performance. The hybrid knowledge model outperforms single-source models, achieving scores of 0.736, 0.952, and 0.937, respectively, while significantly reducing judicial document generation time. This study offers a theoretical and empirical basis for legal AI in Chinese construction disp | G6: SI
A7: 2 | B7: R0082 | C7: Incluido | D7: Measuring Faithfulness and Abstention: An Automated Pipeline for Evaluating LLM-Generated 3-ply Case-Based Legal Arguments | E7: 2025 | F7: Large Language Models (LLMs) demonstrate potential in complex legal tasks like argument generation, yet their reliability remains a concern. Building upon pilot work assessing LLM generation of 3-ply legal arguments using human evaluation, this paper introduces an automated pipeline to evaluate LLM performance on this task, specifically focusing on faithfulness (absence of hallucination), factor utilization, and appropriate abstention. We define hallucination as the generation of factors not present in the input case materials and abstention as the model’s ability to refrain from generating arguments when instructed and no factual basis exists. Our automated method employs an external LLM to extract factors from generated arguments and compares them against the ground-truth factors provided in the input case triples (current case and two precedent cases). We evaluated eight distinct LLMs on three tests of increasing difficulty: 1) generating a standard 3-ply argument, 2) generating an argument with swapped precedent roles, and 3) recognizing the impossibility of argument generation due to lack of shared factors and abstaining. Our findings indicate that while current LLMs achieve h | G7: SI
A8: 3 | B8: R2878 | C8: Incluido | D8: Development of an Automated Construction Contract Review Framework Using Large Language Model and Domain Knowledge | E8: 2025 | F8: Construction contract review demands specialized expertise, requiring comprehensive understanding of both technical and legal aspects. While AI advancements offer potential solutions, two problems exist: LLMs lack sufficient domain-specific knowledge to analyze construction contracts; existing RAG approaches do not effectively utilize domain expertise. This study aims to develop an automated contract review system that integrates domain expertise with AI capabilities while ensuring reliable analysis. By transforming expert knowledge into a structured knowledge base aligned with the SCF classification, the proposed structured knowledge-integrated RAG pipeline is expected to enable context-aware contract analysis. This enhanced performance is achieved through three key components: (1) integrating structured domain knowledge with LLMs, (2) implementing filtering combined with hybrid dense–sparse retrieval mechanisms, and (3) employing reference-based answer generation. Validation using Oman’s standard contract conditions demonstrated the system’s effectiveness in assisting construction professionals with contract analysis. Performance evaluation showed significant improvements, achiev | G8: SI
A9: 4 | B9: R0679 | C9: Incluido | D9: LegalBot-EC: An LLM-Based Chatbot for Legal Assistance in Ecuadorian Law | E9: 2025 | F9: This work presents LegalBot-EC, a domain-specific legal chatbot designed to provide accurate responses grounded in Ecuadorian law. The system combines ChromaDB for contextual retrieval and LLaMA 3.1 as its generative model, ensuring legally relevant and contextually grounded answers. Its knowledge base consists of two key legal documents, the COIP and the 2008 Constitution of Ecuador, which serve as the foundation for response generation. The chatbot was evaluated through two key assessments: user satisfaction and accuracy measurement. A satisfaction study conducted with final-year university students specializing in law resulted in an average score of 88.72 out of 100, indicating strong approval in terms of correctness, relevance, and clarity. Additionally, an accuracy assessment based on 25 legal queries demonstrated robust performance, with 23 correct responses, 2 partially correct responses, and none classified as incorrect, yielding a weighted accuracy of 96%. Furthermore, qualitative tests confirm the chatbot’s ability to generate well-structured, legally sound responses, even when queried in English, demonstrating multilingual capabilities. | G9: SI
A10: 5 | B10: R0102 | C10: Incluido | D10: A Rule-Guided Retrieval-Augmented Framework for Intelligent Contract Review Based on Clause-Type Classification | E10: 2026 | F10: Large language models (LLMs) have shown potential in legal text processing, but direct LLM-based contract review remains limited by hallucinated findings, unstable rule matching, redundant outputs, and weak traceability. This paper proposes a rule-guided retrieval-augmented framework for intelligent contract review based on clause-type classification. The framework segments contracts into clause-level units, classifies each clause into predefined types, retrieves audit rules through clause-type filtering, keyword matching, semantic retrieval, and reranking, and generates traceable review findings with revision suggestions. A human-in-the-loop mechanism is introduced to support professional oversight and reduce unsupported conclusions. A pilot evaluation on equipment procurement and sales contracts compares the proposed method with DeepSeek-only and vanilla RAG baselines. The results indicate that clause-type-guided retrieval improves audit rule matching, enhances risk detection, reduces redundant findings, and strengthens the traceability of generated outputs. This study provides a practical and explainable approach for applying LLMs to legal contract review. | G10: SI
A11: 6 | B11: R0016 | C11: Incluido | D11: A New Metadata-Aware Retrieval-Augmented Generation (RAG) Architecture for Trustworthy Legal Question Answering | E11: 2026 | F11: Large Language Models (LLMs) offer strong capabilities for Natural Language Processing, yet their inherent uncertainty often produces hallucinations, confident but incorrect statements, which is critical in domains requiring precise knowledge representation. Retrieval-Augmented Generation (RAG) reduces this risk through information retrieval, but standard pipelines still suffer from fragmented context and weak alignment between queries and legal provisions, limiting trustworthy knowledge extraction. This study proposes a Metadata-Aware RAG architecture to improve grounding in large legal corpora. It integrates: 1) Sub-chunking with Legal Metadata Inheritance, which transforms unstructured legal PDFs into granular, metadata-rich fragments; and 2) an Adaptive Filter Creator, a pipeline that extracts structured constraints and compiles optimized hybrid retrieval queries. These components enhance semantic alignment, reduce uncertainty-driven hallucinations, and strengthen neural information retrieval. Using a curated Peruvian labor law corpus and 150 manually validated question–answer pairs, the system was evaluated across three LLMs (Llama-3.1-8B, GPT-OSS-20B, Gemma-3-27B). The propos | G11: SI
A12: 7 | B12: R0052 | C12: Incluido | D12: Hallucination-Free? Assessing the Reliability of Leading AI Legal Research Tools | E12: 2025 | F12: Legal practice has witnessed a sharp rise in products incorporating artificial intelligence (AI). Such tools are designed to assist with a wide range of core legal tasks, from search and summarization of caselaw to document drafting. However, the large language models used in these tools are prone to “hallucinate,” or make up false information, making their use risky in high-stakes domains. Recently, certain legal research providers have touted methods such as retrieval-augmented generation (RAG) as “eliminating” or “avoid[ing]” hallucinations, or guaranteeing “hallucination-free” legal citations. Because of the closed nature of these systems, systematically assessing these claims is challenging. In this article, we design and report on the first preregistered empirical evaluation of AI-driven legal research tools. We demonstrate that the providers' claims are overstated. While hallucinations are reduced relative to general-purpose chatbots (GPT-4), we find that the AI research tools made by LexisNexis (Lexis+ AI) and Thomson Reuters (Westlaw AI-Assisted Research and Ask Practical Law AI) each hallucinate between 17% and 33% of the time. We also document substantial differences bet | G12: SI
A13: 8 | B13: R2698 | C13: Incluido | D13: Long-Document RAG for Contractual and Insurance Clause Analysis in Receivables RWA Structures | E13: 2024 | F13: Receivables real-world-asset (RWA) structures require repeated verification of master receivables purchase agreements, insurance policies, repurchase language, default triggers, and dilution-risk provisions. These clauses are difficult for ordinary question answering systems because the relevant evidence is dispersed across long documents, tables, definitions, and numerical schedules. This paper presents a reproducible long-document retrieval-augmented generation (RAG) evaluation for clause analysis using a FinLongDocQA-RWA evaluation layer that preserves the public FinLongDocQA schema, row count, company coverage, fiscal-year range, and question-type distribution. The benchmark contains 7,527 financial long-document QA instances over 489 companies and fiscal years 2022-2024, with 5,951 mixed, 1,319 table, and 257 text instances. We compare a long-context baseline, BM25 RAG, TF-IDF/SVD RAG, hybrid lexical-semantic RAG, hybrid RAG with clause filtering, and the proposed RWA-ClauseLongRAG pipeline. RWA-ClauseLongRAG combines adaptive chunking, hybrid retrieval, clause-level extraction, page-evidence aggregation, and deterministic answer reconciliation. Across all 7,527 instances, it | G13: SI
A14: 9 | B14: R0021 | C14: Incluido | D14: Grounded in Law: A Multi-Stage Anti-Hallucination Pipeline for Legal RAG Systems in Brazilian Portuguese | E14: 2026 | F14: Large Language Models (LLMs) are effective text generators but create legal citations at non-trivial rates, a failure mode with serious consequences in legal practice. In Brazilian Portuguese the risk is amplified by citation variability (juridiquês), fragment-level references (article → paragraph → item), and the need to distinguish jurisdictions and court instances. We describe EscavAI, a production Retrieval-Augmented Generation (RAG) system deployed at Escavador, a Brazilian legal-technology platform. The system combines (1) domain-tuned hybrid retrieval (lexical, dense, and cross-encoder reranking) over a large-scale legal corpus; (2) grounded generation with explicit citation constraints; and (3) a post-generation Reference Audit layer that extracts legislation and jurisprudence mentions via specialized taggers, normalizes them to a canonical schema, checks existence against authoritative databases at fragment granularity, verifies fidelity against official texts, and triggers targeted rewrites when inconsistencies are detected. We report production telemetry from 184,895 audited answers containing 43,175 extracted legal references. Legislation references resolve at 81.7%, wh | G14: SI
A15: 10 | B15: R0037 | C15: Elegibilidad E7 | D15: Precedent Aware Legal Reasoning System for Turkish Jurisdiction with RAG Supported LLMs | E15: 2025 | F15: Large Language Models have achieved impressive progress in natural language processing, yet their tendency to hallucinate undermines reliability in high-stakes domains such as law. This paper presents a precedent-grounded Retrieval-Augmented Generation framework for legal question answering in the Turkish judicial system. The framework integrates dense retrieval with domain-tuned embeddings and sparse retrieval with BM25 and introduced two domain-adapted models: LexiTurk111M for retrieval and LexiTurk-14B for generation. Compared to strong baselines, the system delivers clear gains in retrieval accuracy, answer correctness, and faithfulness, while substantially reducing hallucinations. In particular, LexiTurk14B outperforms its base Qwen3-14B, with correctness increasing from 2.10 to 3.10 in closed-book and 4.23 with RAG. These results highlight the effectiveness of precedent-grounded RAG and establish a reproducible path toward explainable and trustworthy legal AI in under-resourced languages. © 2025 IEEE. | G15: SI
A16: 11 | B16: R0471 | C16: Elegibilidad E7 | D16: Detecting Transitional Provisions in EU Legislation with Hybrid AI for Better Regulation | E16: 2025 | F16: Maintaining an accessible and up-to-date legislative framework is crucial for ensuring transparent governance and enabling effective citizen participation in democratic processes. This paper examines methodological approaches for the automated detection and modeling of textual modifications within EU Regulations and Directives, with particular attention to transitional provisions and temporal concepts (retroactivity, postponement, relative dates), as well as legislative ones (entry into force, application, sunset clause). We present a comparative analysis of four distinct approaches: (1) a rule-based pipeline utilizing regular expressions to capture standardized legal expressions, (2) a SpaCy-based pipeline leveraging advanced NLP capabilities for entity recognition and pattern matching, (3) a Large Language Model (LLM)-based pipeline using the OpenRouter API for contextual extraction, and (4) RDF/Cellar extraction serving as the benchmark. Each methodology is designed to generate standardized Akoma Ntoso (AKN) metadata annotations, facilitating point-in-time understanding of legislative modifications and temporal validity. The rule-based and SpaCy-based approaches offer computatio | G16: SI
A17: 12 | B17: R0468 | C17: Elegibilidad E7 | D17: Evidence-First Structured Generation: A Two-Stage "Extract-Generate" Minimization Framework for Power Regulation Question Answering | E17: 2025 | F17: The auditability and reproducibility of answers are vital for safety and compliance in power regulation question answering. However, current approaches often lack evidence traceability, involve high costs in fine-tuning and deploying large models, and exhibit poor format adaptability. To overcome these limitations, we introduce an Evidence-First, two-stage extract-generate framework. Its first stage employs a dual-track retrieval strategy combining BM25 and vector retrieval to obtain candidate clauses, from which a fine-tuned model extracts key evidence snippets. These extracted snippets, along with associated metadata including clause numbers, versions, source URLs and confidence scores, are passed to the second stage. The second stage uses predefined templates to integrate this evidence with metadata for structured answer generation. Utilizing LORA for parameter-efficient fine-tuning, the framework updates only a minimal fraction of parameters, creating a stable retrieve-extract-generate loop. Experiments on 1069 power regulations and a DuReader-robust subset show our method achieves 88.7% evidence completeness and 89.3% format consistency under comparable resources, outperformin | G17: SI
... A47: 42 | B47: R0122 | C47: Elegibilidad E6 | D47: Verifiable Legal Contract Question Answering Using Natural Language Inference Grounding and Knowledge Graphs | E47: 2026 | F47: Legal contract analysis is a critical yet labor-intensive process in the legal and business domains where precise interpretation of complex contractual language is required. Existing approaches to automated legal question answering (QA) suffer from hallucination, lack of verifiability, and inability to provide traceable reasoning. This work provides a hybrid neural and structured-verification pipeline that combines retrieval-augmented generation with multi-signal verification to produce accurate, verifiable answers from legal contracts. This system integrates a FAISS-based semantic retrieval engine using Sentence Transformers for clause-level retrieval, a Qwen 2.5-7B language model fine-tuned with Supervised Fine-Tuning (SFT) for structured legal tool-calling reasoning and fine-tuned DeBERTa-v3 Natural Language Inference (NLI) model for verification. The pipeline concludes with confidence gating that flags low-confidence answers, preventing silent hallucination. | G47: No
A48: 43 | B48: R2350 | C48: No recuperado | D48: Generative AI Hallucinations and Legal Liability in Jordanian Civil Courts: Promoting the Responsible Use of Conversational Chat Bots | E48: 2024 | G48: No
A49: 44 | B49: R2659 | C49: No recuperado | D49: Automate Text Processing for Schematically Analyzing Legal Texts | E49: 2024 | G49: No
A50: 45 | B50: R1847 | C50: Cribado E3 (manual) | D50: Green Industrial Policy and Sustainable Development in Emerging Markets: A Multi-Agent Decision-Support System with International-Law Source Ranking for Evidence-Grounded Cross-Border Green Product Requirements | E50: 2026 | F50: Emerging-market exporters encounter global sustainability governance not as a treaty or a target but as a product rule: an energy performance threshold, a restricted-substance limit, and a recyclability declaration. Those rules are published, and publication is not the same as access. A firm with a regulatory affairs department can establish which version of a measure is in force, which products it covers and what evidence the destination market will accept; the small- and medium-sized enterprises that dominate emerging-market export bases usually cannot, so rules written to raise environmental standards can exclude the firms least equipped to read them. This paper asks whether emerging digital technologies can convert the transparency infrastructure of the trading system into sustainable business capability. We develop GRACE, a WTO-informed decision-support system that resolves regulatory versions and timelines before interpretation begins, ranks evidence by the authority of its source, declines to state any obligation that no official passage supports, and escalates to human experts when the record is incomplete. Evaluation covers 214 held-out notification families under family-l | G50: No
A51: 46 | B51: R1529 | C51: Cribado E3 (manual) | D51: Governance of Generative AI | E51: 2025 | F51: The rapid and widespread diffusion of generative artificial intelligence (AI) has unlocked new capabilities and changed how content and services are created, shared, and consumed. This special issue builds on the 2021 Policy and Society special issue on the governance of AI by focusing on the legal, organizational, political, regulatory, and social challenges of governing generative AI. This introductory article lays the foundation for understanding generative AI and underscores its key risks, including hallucination, jailbreaking, data training and validation issues, sensitive information leakage, opacity, control challenges, and design and implementation risks. It then examines the governance challenges of generative AI, such as data governance, intellectual property concerns, bias amplification, privacy violations, misinformation, fraud, societal impacts, power imbalances, limited public engagement, public sector challenges, and the need for international cooperation. The article then highlights a comprehensive framework to govern generative AI, emphasizing the need for adaptive, participatory, and proactive approaches. The articles in this special issue stress the urgency of d | G51: No
A52: 47 | B52: R0344 | C52: Cribado E3 (manual) | D52: TSAC-RAG: Type- and Structure-Aware Constraint Retrieval for Question Answering over Power-System Standards | E52: 2026 | F52: Power-system technical standards provide the engineering basis for substation design, equipment acceptance, operation and maintenance, relay protection, and grid security control. Large language models (LLMs) offer a convenient interface to this knowledge, but their answers may be unreliable when requirements vary with equipment type, voltage level, operating condition, numerical limit, physical unit, or clause scope. This paper proposes TSAC-RAG, a type- and structure-aware retrieval-augmented generation framework for question answering over power-system standards. It combines lexical relevance, numerical–unit consistency, clause hierarchy, and question-type information to retrieve and rerank applicable clauses. The evidence is then supplied to an instruction-tuned LLM for engineering interpretation and citation-grounded answer generation. An audit of EleQA identifies 31,181 nonempty clauses and 18,584 questions with exact evidence mappings. Across three balanced test samples, TSAC-RAG achieves 83.82 ± 0.54% Recall@1, 96.81 ± 0.03% Recall@10, and 88.73 ± 0.28% MRR@10, improving over the strongest unconstrained retriever by 1.31, 0.50, and 1.11 percentage points. The results show t | G52: No
A53: 48 | B53: R0960 | C53: Cribado E3 (manual) | D53: RAIM: Operationalizing Trustworthy AI in Music Generation | E53: 2026 | F53: Generative AI is radically reshaping the musical landscape, unlocking new forms of creative expression while simultaneously raising profound ethical, legal, and societal concerns. Key among these are the potential displacement of human creativity, copyright infringement stemming from vast training datasets, and the lack of transparency, explainability, and fairness mechanisms. As generative systems become pervasive, shifting from reactive regulation to responsible design is crucial. While previous work has tackled isolated aspects of generative systems, we propose a systematic framework grounded in the Ethics Guidelines for Trustworthy AI produced by the European Commission’s High-Level Expert Group. Focusing on generative music AI, we contextualize these requirements into 45 responsible features that address trustworthiness across technical, legal, and artistic dimensions. We evaluate this framework through a multi-stage Delphi study involving a global panel of experts from academia, industry, and regulatory bodies, comprising AI ethicists, legal experts, music AI practitioners, and artists. The results demonstrate a high degree of expert endorsement for the proposed features, whi | G53: No
A54: 49 | B54: R1915 | C54: Cribado E3 (manual) | D54: Should I and Can I Use AI for Forensic Psychiatry Report Writing? | E54: 2026 | F54: Abstract The rapid evolution of AI, particularly large language models (LLMs), has renewed interest in their potential role in forensic psychiatry report writing. Recent evidence demonstrates that contemporary LLMs perform well in selected medical knowledge, documentation, and information management tasks and may reduce the administrative burden when deployed under appropriate clinical supervision. However, forensic psychiatric reports differ fundamentally from routine clinical documentation. They constitute expert evidence prepared for legal proceedings and therefore require transparent reasoning, explicit weighing of competing evidence, a robust factual foundation, and personal professional accountability. This viewpoint examines whether AI can and should be used in forensic psychiatry report writing by integrating recent empirical evidence, forensic psychiatry guidance, legal and regulatory frameworks, and emerging governance recommendations. Rather than comparing AI with an idealized human evaluator, the manuscript argues that the appropriate comparison is between 2 imperfect systems of reasoning. Human experts remain susceptible to cognitive biases, omission errors, and disagr | G54: No
A55: 50 | B55: R0223 | C55: Cribado E3 (manual) | D55: Rethinking Strategic Mechanism Design in the Age of Large Language Models: New Directions for Communication Systems | E55: 2025 | F55: This paper explores the application of large language models (LLMs) in designing strategic mechanisms -including auctions, contracts, and games- for specific purposes in communication networks. Traditionally, strategic mechanism design in telecommunications has relied on human expertise to craft solutions based on game theory, auction theory, and contract theory. However, the evolving landscape of telecom networks, characterized by increasing abstraction, emerging use cases, and novel value creation opportunities, calls for more adaptive and efficient approaches. We propose leveraging LLMs to automate or semi-automate the process of strategic mechanism design, from intent specification to final formulation. This paradigm shift introduces both semi-automated and fully-automated design pipelines, raising crucial questions about faithfulness to intents, incentive compatibility, algorithmic stability, and the balance between human oversight and artificial intelligence (AI) autonomy. The paper discusses potential frameworks, such as retrieval-augmented generation (RAG)-based systems, to implement LLM-driven mechanism design in communication networks contexts. We examine key challenges, | G55: No
A56: 51 | B56: R2821 | C56: Cribado E3 (manual) | D56: RESPONSIBLE USE OF AI-GENERATED CONTENT IN VIETNAMESE SCHOLARLY PUBLISHING: EVIDENCE FROM JOURNAL POLICIES AND EDITORIAL PRACTICES | E56: 2026 | F56: The rapid diffusion of generative artificial intelligence (GenAI) tools—especially large language models (LLMs)—is reshaping scholarly publishing worldwide. While these tools can support language editing, translation, and workflow efficiency, they also raise integrity risks, including fabricated citations, unverifiable claims, undisclosed ghostwriting, confidentiality breaches in peer review, and contested ownership of AI-assisted outputs. Vietnam’s journal ecosystem is currently navigating internationalization pressures (e.g., indexing and visibility goals) alongside uneven editorial capacity and fragmented policy infrastructure, making it a critical setting for examining responsible governance of AI-generated content (AIGC). This study reports an exploratory policy-and-practice mapping across five Vietnam-affiliated publishing contexts (university-based open access journals, an internationally co-published journal, a defense-related journal, and law/social-science publishing). Using structured qualitative content analysis, we identify shared norms (e.g., “AI cannot be an author,” accountability remains human) but also substantial variation in disclosure requirements, treatment of | G56: No
A57: 52 | B57: R2884 | C57: Cribado E3 (manual) | D57: A Spatiotemporal–Semantic Coupling Intelligent Q&A Method for Land Use Approval Based on Knowledge Graphs and Intelligent Agents | E57: 2025 | F57: The rapid retrieval and precise acquisition of land use approval information are crucial for enhancing the efficiency and quality of land use approval, as well as for promoting the intelligent transformation of land use approval processes. As an advanced retrieval method, question-answering (Q&A) technology has become a core technical support for addressing current issues such as low approval efficiency and difficulty in obtaining information. However, existing Q&A technologies suffer from significant hallucination problems and limitations in considering spatiotemporal factors in the land use approval domain. To effectively address these issues, this study proposes a spatiotemporal–semantic coupling intelligent Q&A method for land use approval based on knowledge graphs (KGs) and intelligent agent technology, aiming to enhance the efficiency and quality of land use approval. Firstly, a land use approval knowledge graph (LUAKG) is constructed, systematically integrating domain knowledge such as policy clauses, legal regulations, and approval procedures. Then, by combining large language models (LLMs) and intelligent agent technology, a spatiotemporal–semantic coupling Q&A framework i | G57: No
A58: 53 | B58: R1475 | C58: Cribado E3 (manual) | D58: Repairing DeFi Vulnerabilities: Benchmarking LLMs with Executable Solidity Exploits | E58: 2025 | F58: Decentralized finance protocols are frequently exploited, creating a demand for fast and reliable repair of vulnerable smart contracts and validation that reflects runtime security. Large language models are an emerging source of patches, yet many evaluations rely on manual checks or self-assessment, which cannot confirm whether attacker profit is actually prevented. We introduce an executable benchmark that replays verified real-world exploits against patched Solidity contracts under a resilient protocol that permits alternate attack paths and controlled state variation. Our framework compiles candidate patches, deploys them on a forked chain, and tests whether the exploit still yields profit. The benchmark covers six test cases drawn from reproducible incidents and is released as open-source. Among the nine evaluated models, GPT-5, GPT-4.1, and Claude Opus 4.1 performed the best, mitigating four of six test cases. Microsoft Phi-4 was the most reliable open-source model, mitigating two of six exploits and producing compilable patches for the remaining cases. No model mitigated the H2O case once resilient checks were enabled, while a simpler access control flaw, BTNFT, was often re | G58: No
A59: 54 | B59: R2708 | C59: Cribado E3 (manual) | D59: A Human-in-the-Loop LLM Agent Framework with LoRA Domain Adaptation for DO-330 TQL-1 Tool Qualification | E59: 2026 | F59: Civil airborne software certification follows RTCA/DO-178C, and tools used in its development and verification must be qualified per RTCA/DO-330. For TQL-1 tools—the highest qualification level—the strict criteria, the demand for detailed process data, and the substantial peer-review effort have become important factors driving program duration and human cost; at the same time, TQL-1 requires verification activities to reach Independence Level 3, which makes fully replacing manual review with AI infeasible on compliance grounds. To safely introduce AI assistance under these airworthiness constraints, we propose a Human-in-the-Loop (HITL) LLM-Agent framework that delegates highly repetitive, rule-bounded compliance pre-screening to the Agent while keeping independent judgment and formal sign-off with human reviewers. The framework comprises three components: (1) a rule-extraction chain that uses DeepSeek-R1 671B to convert project-level TRS/TDS/TCS into a JSON rule set with source-clause-ID provenance; (2) LoRA domain adaptation that applies QLoRA 4-bit fine-tuning to Qwen3-Coder-30B-A3B on a three-source dataset (DeepSeek-R1 distilled synthesis, commercial static-analyzer hits, and | G59: No
A60: 55 | B60: R2791 | C60: Cribado E3 (manual) | D60: Benchmarking large language models for ACMG/AMP variant interpretation and variant calling | E60: 2026 | F60: Agentic large language models are increasingly used across the genomic workflow, from variant calling to clinical interpretation, yet they are evaluated by accuracy alone, a single figure that cannot say whether a system is safe or where in the workflow a failure originates. We present ClawBench, a framework that attributes each outcome to the architectural layer that produced it across both halves of the canonical pipeline. Two design choices remove the confounds that make agentic genomics hard to evaluate: a temporally blinded truth set, in which every scored ClinVar label first became available only after the training cutoff of every model tested, and a fail-closed evidence contract that blocks evidence circular with the truth label. We score validity, safety, provenance and reproducibility, not accuracy alone, under a constraint gradient that relocates correctness from a model’s prior into executed, validated code. We show three things. First, dangerous misclassification is rare and model-invariant, a controlled precondition of the executed architecture rather than a frontier, while fabricated evidence is measurable and is neutralised by execution. Second, different variant cla | G60: No
A61: 56 | B61: R2496 | C61: Cribado E3 (manual) | D61: SafeDep: Detecting State Mutation Unsoundness in Rust via Dependency Slicing and LLM Reasoning | E61: 2026 | F61: Rust's type system protects safe code, but many low-level abstractions depend on internal unsafe operations whose correctness rests on memory and logical invariants. In struct-based abstractions, a sibling method may legally modify internal fields while invalidating a precondition required by another method's unsafe operation. We call this defect an unsound state mutation. Traditional pattern-based static analyzers support inter-procedural tracking but may lack the capability to model cross-method state interference. Furthermore, they cannot interpret natural-language safety contracts, making these deep defects difficult to detect. LLMs can reason about these contracts, but whole-crate prompting is expensive and often prone to hallucinated paths. To bridge this gap, we present SafeDep, a vulnerability discovery framework that combines compiler-driven static analysis with LLM-based semantic reasoning. SafeDep analyzes Rust MIR to build a field-sensitive read/write dependency graph and slices the graph to retain methods that may affect safety-critical state. An LLM then reconstructs cross-method state transitions from this compact context and generates PoC candidates. A bounded compi | G61: No
... A79: 74 | B79: R1634 | C79: Cribado E3 (regla) | D79: Potential Use of ChatGPT-4 in Micronutrient Deficiency Management: A Narrative Scoping Review and a Framework for Validation and Safe Deployment | E79: 2026 | F79: Abstract / Summary Micronutrient deficiencies remain common and clinically important, yet their recognition and management require careful history-taking, appropriate testing, and guideline-concordant counseling. Large language models (LLMs) such as ChatGPT-4 have been proposed as tools that may support clinical nutrition workflows; however, their capabilities and limitations are frequently misunderstood, and their safe use requires rigorous validation. This article provides a narrative scoping synthesis of plausible use cases for ChatGPT-4 across micronutrient deficiency care (e.g., structured symptom–diet–medication history elicitation, drafting clinician-facing summaries, and preparing patient education materials) while explicitly noting that ChatGPT-4 is not an autonomous diagnostic system, does not access real-time biomedical databases, and cannot replace clinician judgment. The authors then propose a practical framework for validation and safe deployment, including task definitions, standardized prompt templates, comparison baselines (clinician-authored outputs and rule-based checklists, and where appropriate predictive machine learning [ML] models), clinician annotation with | G79: No
A80: 75 | B80: R1617 | C80: Cribado E3 (regla) | D80: OntoMetric: An Ontology-Guided Framework for Automated ESG Knowledge Graph Construction | E80: 2025 | G80: No
A81: 76 | B81: R0572 | C81: Cribado E3 (regla) | D81: A Hierarchical Verification Framework for Power Engineering Design Based on LLM-Driven Rule and Knowledge Base Integration | E81: 2025 | F81: This paper presents a hierarchical design verification framework that integrates Large Language Models with structured engineering knowledge to automate power system design validation. The framework employs a three-layer architecture: rule-based compliance checking, technical consistency analysis, and completeness assessment. The system leverages formalized rules from IEEE/IEC standards and maintains citation-backed rationales linking verification decisions to authoritative sources. A case study on a real-world 220 kV substation design project demonstrates the framework's practical applicability, achieving expert-validated 92% accuracy in issue identification across 156 pages of design documentation. The system successfully detected all major compliance issues including protection coordination violations and equipment rating inconsistencies, while identifying additional optimization opportunities. | G81: No
A82: 77 | B82: R0554 | C82: Cribado E3 (regla) | D82: ArgRE: Formal Argumentation for Conflict Resolution in Multi-Agent Requirements Negotiation | E82: 2026 | F82: As software systems grow in complexity, they must satisfy an increasing number of competing quality attributes, making it essential to balance them in a principled manner—for example, a safety requirement for sensor-fusion verification may conflict with a tight planning-cycle budget. Multi-agent large language model frameworks support this balancing process by assigning specialized agents to different objectives. However, their conflict resolution is typically heuristic. Requirements are aggregated implicitly without explicit acceptance or rejection, limiting auditability in regulated domains. We present ArgRE, a multi-agent requirements negotiation system that embeds Dung-style abstract argumentation into the negotiation stage. Each proposal, critique, and refinement is modeled as an argument, conflicts are represented as directed attack relations, and the accepted set of arguments is computed under grounded and preferred semantics. The pipeline further integrates KAOS goal modeling, multi-layer verification, and standards-oriented artifact generation. Evaluation across five case studies spanning safety-critical, financial, and information-system domains shows that ArgRE provides | G82: No
A83: 78 | B83: R0883 | C83: Cribado E3 (regla) | D83: BLIND-TWIN: Blockchain-Assisted LLM-Based Cds for Digital Twin-Enhanced Industrial AIoT | E83: 2025 | F83: The interconnected and diverse nature of Digital Twin (DT)-based industrial Artificial Internet of Things (AIoT) systems exposes them to potential cyber threats and malicious activities. This paper introduces a novel framework called BLIND-Twin, which leverages blockchain, DT, and Large Language Model (LLM) technologies to address critical security and scalability challenges in industrial AIoT networks. By integrating DT technology, BLIND-Twin continuously mirrors physical environments, enabling real-time monitoring and synthetic data generation to simulate diverse threat scenarios. Data from the DT undergoes feature extraction via a Long Short-Term Memory (LSTM) Autoencoder (LSTM-AE) to extract essential temporal patterns, while the LLM enables adaptive, contextaware intrusion detection without retraining. A permissioned blockchain layer ensures data integrity, privacy, and secure logging through smart contracts, supporting automated threat response with verifiable audit trails. The framework's decentralized architecture mitigates Single Points of Failure (SPoF), addressing scalability and privacy concerns. Performance evaluations utilizing datasets like 5G-NIDD and CICIoT2023 dem | G83: No
A84: 79 | B84: R0680 | C84: Cribado E3 (regla) | D84: Traceability and Performance Optimization: Application of Generative AI, Digital Twin, and DRL in the Recycling Process of WEEE | E84: 2024 | F84: The lack of transparency, unified standards, and effective regulation, along with the complexity of the supply chain, make it challenging to achieve reliable traceability throughout the entire process of recycling and reusing waste electronic appliances. This poses a challenge for effectively implementing carbon reduction measures. In response to the above issues, we propose a full process data management solution for WEEE recycling based on blockchain technology. In addition, a method combining digital twin and generative AI technology has been proposed to address the performance bottleneck issue of blockchain. Predicting future data flow through generative AI models and utilizing reinforcement learning algorithms to predictively optimize blockchain parameter configurations effectively improve blockchain performance and scalability. The experimental results demonstrate that the proposed method effectively enhances system adaptability and throughput. It achieves an integration of reliable traceability, accurate prediction, and performance optimization throughout the entire process of WEEE recycling and reuse data management. | G84: No
A85: 80 | B85: R0847 | C85: Cribado E3 (regla) | D85: Cognitive Security Risks and Countermeasures of Generative Artificial Intelligence in Education Management | E85: 2026 | F85: Generative artificial intelligence (GenAI) is rapidly transforming education management through advanced content generation, reasoning, and autonomous decision-support capabilities. While these technologies promise significant gains in efficiency, personalization, and scalability, their deployment also introduces a class of cognitive security risks that extend beyond traditional cybersecurity and data privacy concerns. These risks directly affect human cognition, judgment, learning integrity, and institutional governance, yet remain insufficiently systematized in existing research. This paper presents a comprehensive analysis of cognitive security in GenAI-enabled education management from a socio-technical and engineering management perspective. We propose a three-tiered taxonomy that categorizes risks into 1) internal security (model vulnerabilities such as jailbreaks, backdoors, and data poisoning), 2) interactional security (hallucination, bias, data leakage, and intellectual property infringement arising from human–AI interaction), and 3) external security (the weaponization of GenAI for fraud, disinformation, deepfakes, and malicious automation). Building on this taxonomy, we | G85: No
A86: 81 | B86: R2200 | C86: Cribado E3 (regla) | D86: Applications of DeepSeek in Medicine: Bibliometric Analysis and Scoping Review | E86: 2026 | F86: Abstract Background The integration of large language models (LLMs) into medicine has reshaped health care delivery, education, and research. Although proprietary models face challenges such as data privacy, regulation, and adaptability, DeepSeek, an open-source LLM, has emerged as a customizable and cost-effective alternative with significant potential for clinical and operational applications. However, the rapid expansion of research in this area necessitates a systematic mapping of its landscape, applications, and challenges. Objective This study combines bibliometric analysis with a scoping review to systematically map and characterize the literature on DeepSeek’s medical applications. The aims were to (1) analyze publication trends, leading contributors, and research themes and (2) identify primary application domains, strengths, limitations, and future directions. Methods Following the framework by Arksey and O’Malley and the PRISMA-ScR (Preferred Reporting Items for Systematic Reviews and Meta-Analyses Extension for Scoping Reviews) guidelines, a systematic search was conducted using PubMed, Web of Science, and Scopus from January 20, 2025, to November 30, 2025. Bibliometric | G86: No
A87: 82 | B87: R0460 | C87: Cribado E3 (regla) | D87: Multi-Agent Auditing for Smart Contracts* | E87: 2025 | F87: Smart contracts underpin contemporary decentralized systems, yet their immutability and perpetual execution amplify the consequences of latent defects. Despite progress in manual audits, static analysis, fuzzing, and formal verification, auditors face a widening gap between the scalability and desired assurance due to limited automation capability. Recent large language models (LLMs) with tool-use capabilities promise greater automation, but monolithic single-agent auditors struggle with coverage, robustness, and reproducibility. Motivated by addressing these issues, we propose Multi-Agent Auditing (MAA), a framework that coordinates a team of tool-grounded agents through a constrained protocol that privileges verifiable artifacts. Besides, we mechanize an LLM-assisted orchestration mechanism and a shared knowledge base to coordinate a set of agents specialized in sophisticated testing approaches to produce budget-aware and evidence-centric audit results. Furthermore, we present the experiment results showing that MAA outperforms singleLLM auditors and provide empirical insights into LLM-backend selection. | G87: No
A88: 83 | B88: R0019 | C88: Cribado E3 (regla) | D88: RAG in Specialized Domains: A Survey of QA Chatbots | E88: 2026 | F88: This paper explores the evolution of large language models (LLMs) and the growing role of retrieval-augmented generation (RAG) systems in overcoming challenges in domain-specific applications. Although LLMs have revolutionized natural language processing (NLP), they face critical limitations in high-stakes domains such as medicine, engineering, and law where accuracy, factuality, and trust are paramount. These shortcomings include hallucinations, outdated knowledge, and vulnerability to adversarial prompts. RAG systems address these issues by integrating LLMs with external domain-specific knowledge sources to improve factual grounding and response reliability. Frameworks like Almanac in clinical settings and KEAG in complex QA tasks demonstrate how RAG reduces hallucinations, enhances interpretability, and delivers accurate, evidence-backed responses. In healthcare, combining LLMs with RAG has raised accuracy from around 93.25% up to 99.25%, showing its impact on real-world decision support. This paper proposes a structured synthesis of advancements, challenges, and optimization strategies in RAG for specialized domains, paving the way for safer, transparent, and adaptive AI system | G88: No
A89: 84 | B89: R0474 | C89: Cribado E3 (regla) | D89: Self-Auditing LLMs for Bias and Hallucination Reduction Through Multi-Agent Frameworks | E89: 2026 | F89: Large Language Models (LLMs) have demonstrated exceptional performance across a wide range of natural language processing tasks; however, their real-world deployment is constrained by persistent challenges such as hallucinated content, biased outputs, and logically inconsistent reasoning. These shortcomings significantly undermine the reliability, transparency, and trustworthiness of LLM-driven systems, particularly in high-stakes domains including healthcare, finance, law, and scientific research. This paper presents a Self-Auditing Multi-Agent Framework that enables an LLM to autonomously evaluate, critique, and refine its own responses prior to final delivery. The proposed architecture decomposes a single LLM into multiple specialized auditing agents tasked with factual verification, bias and fairness assessment, reasoning consistency analysis, and confidence estimation. The outputs of these agents are integrated through a closed-loop correction mechanism that iteratively improves response quality and robustness. Experimental results demonstrate that the framework substantially reduces hallucinations, enhances logical coherence, and improves overall output reliability without re | G89: No
A90: 85 | B90: R2521 | C90: Cribado E3 (regla) | D90: Beyond Detection: Large Language Models and Next-Generation Cybersecurity | E90: 2025 | F90: The Integrating Contextual and Adaptive Cyber Defense Systems The accelerating evolution of cyber threats, seen both in terms of their complexity and frequency of attempts, makes it imperative to move away from traditional, reactive defense structures and towards intelligent, adaptive and proactive cyber defense strategies. Large Language Models (LLMs) (such as GPT this-will-be-a-zillionth-of-a-second-type-here or BERT derivatives) represent powerful new capabilities developed for understanding, analyzing, and generating human-like language with contextual depth enabling a new frontier in the land of cyber defense. This survey investigates the influence of LLMs on multiple key technical areas of cybersecurity including software and system security, network security, content moderation, hardware security, and blockchain security. It showcases applications of LLMs in tasks in vulnerability detection and prevention, phishing, malware detection and analysis, and intrusion detection; as well as smart contract auditing and adversarial attack simulation. The paper goes more in-depth on technical constructs like zero-shot and few-shot threat hunting, prompt engineering for scenario modelin | G90: No
A91: 86 | B91: R0312 | C91: Cribado E3 (regla) | D91: Can Herpes Zoster Vaccine Reduce Alzheimer's Disease Risk? A KG and LLMS Synergistic Integration Approach | E91: 2025 | F91: Current research reveals that the herpes zoster vaccine(HZV) can effectively prevent and mitigate Alzheimer's disease(AD). However, the underlying mechanisms linking the HZV and AD remain incompletely understood. We employ a literature-based discovery (LBD) paradigm to investigate these mechanisms. Traditional knowledge graph-based approaches demonstrate strong performance in implicit knowledge discovery tasks. However, existing methods still face critical challenges: (1) The diverse representations of biomedical entities often degrade knowledge graph quality, such as introducing path redundancy; (2) Current path-ranking mechanisms lack rigorous biological plausibility assessment, resulting in a high number of false-positive paths being retained. To address the aforementioned challenges, this paper proposes a Synergistic Integration framework of Knowledge graphs and Large language models (SIKL). First, the PubTator3.0 tool and manual rule-based methods are employed to extract entities and relational triples from abstract content. A knowledge graph is constructed with medical subject headings as nodes, integrating multiple attributes and relations, effectively mitigating path redund | G91: No
A92: 87 | B92: R2154 | C92: Cribado E3 (regla) | D92: Evaluating knowledge graph enhanced retrieval augmented generation for automated functional requirements extraction | E92: 2026 | F92: The automation of requirements engineering using large language models offers significant potential for efficiency but struggles with hallucinations and a lack of domain-specific precision in highly regulated fields such as healthcare. While retrieval augmented generation (RAG) addresses some of these issues, standard vector-based retrieval often fails to capture complex semantic relationships required for strict compliance. This research assesses the effectiveness of automated functional requirement extraction by comparing two distinct retrieval architectures: a baseline vector-only RAG versus a knowledge graph-enhanced RAG with three distinct prompt strategies. We implemented an end-to-end automated extraction pipeline applied to a corpus of heterogeneous healthcare documents. The study constructed two separate knowledge bases to perform a comparative analysis. Under the experimental conditions (seven healthcare documents, three security-focused testing areas, and Claude3-Haiku at temperature zero), knowledge base curation was found to be a stronger determinant of extraction quality than retrieval architecture, though the relative impact may vary with corpus scale, domain, and ba | G92: No
... A155: 150 | B155: R0940 | C155: Automatización A2 | D155: RO-SVD: A Reconfigurable Hardware Copyright Protection Framework for AIGC Applications | E155: 2024 | F155: The dramatic surge in the utilisation of generative artificial intelligence (GenAI) underscores the need for a secure and efficient mechanism to responsibly manage, use and disseminate multidimensional data generated by artificial intelligence (AI). In this paper, we propose a blockchain-based copyright traceability framework called ring oscillator-singular value decomposition (RO-SVD), which introduces decomposition computing to approximate low-rank matrices generated from hardware entropy sources and establishes an AI-generated content (AIGC) copyright traceability mechanism at the device level. By leveraging the parallelism and reconfigurability of field-programmable gate arrays (FPGAs), our framework can be easily constructed on existing AI -accelerated devices and provide a low-cost solution to emerging copyright issues of AIGC. We developed a hardware-software (HW /SW) co-design prototype based on comprehensive analysis and on-board experiments with multiple AI-applicable FPGAs. Using AI-generated images as a case study, oyr framework demonstrated effectiveness and emphasised customisation, unpredictability, efficiency, manage-ment and reconfigurability. To the best of our kn | G155: No

Sheet Search_Log
A1: Fuente | B1: Fecha de búsqueda | C1: String exacto ejecutado | D1: Campos / filtros | E1: Total mostrado por la plataforma | F1: Registros exportados (fórmula) | G1: Columna PRISMA | H1: Nota
A2: Scopus | B2: 18/10/2026 | C2: TITLE-ABS-KEY(...) AND PUBYEAR > 2019 AND PUBYEAR < 2027 | D2: Título, abstract, keywords | E2: 100 | F2: =COUNTIF(Registros!B:B,"Scopus") -> 100 | G2: Bases de datos | H2: Total confirmado por el investigador (100).
A3: IEEE Xplore | B3: 18/10/2026 | C3: ("All Metadata":...) — pegar string final | D3: All Metadata; año 2020–2026 | E3: 907 | F3: =COUNTIF(Registros!B:B,"IEEE Xplore") -> 907 | G3: Bases de datos | H3: Confirmar si se corrió con regulat* o con la versión restringida.
A4: Semantic Scholar | B4: 18/10/2026 | C4: bulk search: (...)+(...)+(...) | D4: Título, abstract; year=2020- | E4: 1903 | F4: =COUNTIF(Registros!B:B,"Semantic Scholar") -> 1903 | G4: Bases de datos | H4: Incluye registros de arXiv y ACL Anthology.
A5: SciELO | B5: 18/10/2026 | C5: ("modelo de lenguaje" OR "modelos de lenguaje" OR "inteligencia artificial generativa" OR "IA generativa" OR "generación aumentada por recuperación" OR LLM OR RAG OR ChatGPT OR "large language model" OR "generative AI" OR "retrieval-augmented generation") AND (atribuci$ OR cita$ OR verificab$ OR alucinaci$ OR trazab$ OR fundamentaci$ OR attribution OR citation$ OR hallucination$ OR grounding OR faithfulness OR traceab$) AND (contrat$ OR cláusula$ OR clausula$ OR fideicomiso$ OR fiduciari$ OR regulaci$ OR contract$ OR clause$ OR regulat$) | D5: Todos los índices; sin filtros | E5: 3 | F5: =COUNTIF(Registros!B:B,"SciELO") -> 3 | G5: Bases de datos | H5: Prueba piloto previa (sin comillas ni bloque de dominio) devolvió 0; se corrigió la sintaxis antes de la búsqueda final. La exportación no incluye abstracts.
A6: Web of Science | B6: 18/10/2026 (intento) | C6: TS=(("large language model*" OR LLM OR "generative AI" OR "retrieval-augmented generation" OR RAG) AND (attribut* OR citation* OR verifiab* OR hallucinat* OR grounding OR faithfulness OR traceab*) AND (contract* OR clause* OR "legal drafting" OR regulat* OR fiduciar*)) AND PY=(2020-2026) | D6: Core Collection; TS = título, abstract, keywords | E6: No ejecutado | F6: No ejecutado | G6: Bases de datos | H6: No ejecutado: sin acceso institucional (la cuenta personal solo habilita la búsqueda de investigadores). String preparado y documentado para la revisión doctoral completa; se declara como limitación.
A7: SSRN | B7: 18/10/2026 | C7: Consultas cortas (una fila por consulta) | D7: Title, Abstract & Keywords | E7: 2 | G7: Otros métodos | H7: 2 resultados; ambos registrados en Otros_metodos.
A8: Consensus | B8: 18/10/2026 | E8: 20 | G8: Otros métodos | H8: Buscador con IA; no reproducible con string booleano. c2_report es subconjunto de C_report.
A9: Estudios semilla D3 | C9: — | D9: — | E9: 5 | G9: Otros métodos | H9: Magesh 2025, Wang 2025, Wallat 2025, Ju & Lee 2026, Narayanan & Singh 2026.

Sheet Registros
A1: rec_id | B1: fuente | C1: id_fuente | D1: titulo | E1: autores | F1: anio | G1: venue | H1: tipo | I1: doi | J1: arxiv | K1: duplicado_de | L1: criterio_dup | M1: abstract
A2: R0001 | B2: Scopus | C2: 2-s2.0-105045454948 | D2: Beyond Accuracy: Evaluating LLMs for Evidentiary Use in Legal Contexts | E2: Narayanan S.; Potel M.; Mithal V. | F2: 2026 | G2: Artificial Intelligence and Legal Evidence: The Indian Policy and Perspective | H2: Book chapter | I2: 10.1201/9781003629146-2 | M2: Large Language Models (LLMs) are increasingly reshaping the legal domain, presenting substantial potential for various tasks, including legal research, judgment “prediction,” and document drafting. Although specialized/domain-specific LLMs and Retrieval-Augmented Generation (RAG) are designed to enhance performance, general-purpose LLMs demonstrate significant limitations, such as a deficiency in specialized legal knowledge, vulnerability to “hallucinations,” and the perpetuation of biases inherent in training data. This chapter clarifies the distinct challenges associated with deploying LLMs in high-stakes legal applications, with a particular emphasis on contract clause generation. Principal concerns encompass adapting to evolving legal landscapes across jurisdictions, ensuring data privacy and security, addressing biases (e.g., gender stereotypes, jurisdictional inclinations), balancing automation with human oversight, standardizing language while maintaining flexibility, managing multi-jurisdictional complexities, and addressing issues such as accountability for errors. To mitigate these limitations, we propose a comprehensive use-case context-specific evaluation framework, CLAUSE, for contract clause generators. This framework transcends traditional accuracy metrics, evaluating solutions across six critical dimensions: (1) Compliance and Jurisdictional Adaptability, (2) Legal Competence and Reasoning, (3) Accuracy, Reliability, and Trustworthiness, (4) Understanding Context, (5) Structured Contract Elements Handling, and (6) Ethics, Privacy, and Accountability. The CLAUSE framework underscores the essential role of rigorous human-centric evaluation and continuous oversight for the safe, effective, and responsible integration of LLMs into legal practice, thereby ensuring trustworthy AI for evidentiary use. © 2026 selection and editorial matter, Edited by Sarfaraz Ahmed Khan, Lovely Dasgupta, Saptarshi Ghosh and Kripabandhu Ghosh; individual chapters, the contributors.
A3: R0002 | B3: Scopus | C3: 2-s2.0-105026283627 | D3: Conversational Agents: From RAG to LTM | E3: Zhang D.; Feng Y.; Liu H.; Sun C.; Luo J.; Chen X.; Li X. | F3: 2025 | G3: SIGIR-AP 2025 - Proceedings of the 2025 Annual International ACM SIGIR Conference on Research and Development in Information Retrieval in the Asia Pacific Region | H3: Conference paper | I3: 10.1145/3767695.3769671 | M3: Large Language Models (LLMs) have significantly advanced Artificial Intelligence (AI), demonstrating impressive capabilities in language understanding, reasoning, and generation. However, their fixed context windows fundamentally limit their utility in sustained, complex human-computer interactions, leading to issues such as forgetting previous turns, lacking consistent personas, and an inability to perform long-horizon reasoning. While Retrieval-Augmented Generation (RAG) offers a promising solution by externalizing knowledge and providing LLMs with relevant information from external corpora, its traditional static retrieve-then-generate pipeline often struggles with dynamic knowledge integration, introduces noise, and overlooks structural relationships. This tutorial introduces the evolution from traditional RAG to advanced Long-Term Memory (LTM) mechanisms that equip LLM-based conversational agents with human-like memory capabilities. We will explore various LTM architectures, including textual, graph-based, and parametric memory, detailing their forms, operations (such as dynamic indexing, retrieval, updating, and consolidation), and multimodal integration strategies. The tutorial will cover cutting-edge systems (like Mem0), illustrating how they enable agents to maintain coherent conversations, personalize interactions, and perform complex reasoning over extended periods. We will also delve into evaluation benchmarks (e.g., LoCoMo and ZH-4O) as well as metrics that comprehensively assess these long-term memory capabilities. Finally, we will discuss current limitations and promising future research directions, particularly focusing on AI self-evolution, multimodal memory, and ethical considerations. This tutorial aims to provide a comprehensive understanding for researchers and practitioners interested in building the next generation of intelligent, memory-aware conversational AI agents. © 2025 Owner/Author.
A4: R0003 | B4: Scopus | C4: 2-s2.0-85204632333 | D4: Large Language Models in Modern Forensic Investigations: Harnessing the Power of Generative Artificial Intelligence in Crime Resolution and Suspect Identification | E4: Nikolakopoulos A.; Evangelatos S.; Veroni E.; Chasapas K.; Gousetis N.; Apostolaras A.; Nikolopoulos C.D.; Korakis T. | F4: 2024 | G4: EEITE 2024 - Proceedings of 2024 5th International Conference in Electronic Engineering, Information Technology and Education | H4: Conference paper | I4: 10.1109/eeite61750.2024.10654427 | M4: Large Language Models (LLMs) have recently captured the attention of the scientific c ommunity. S ince t he global launch of LLM-based chatbots in late 2022, the field h as witnessed a rapid increase in interest from researchers, technology providers and citizens alike. With its wide-ranging applicability, Generative Artificial I ntelligence (GenAI) h as t he p otential to impact various aspects of society, from improving communication and accessibility to transforming industries such as healthcare, education and security. More specifically, in the field of Forensic Science, LLMs could offer significant b enefits as sisting Law Enforcement Agencies (LEAs) and Forensic Practitioners in crime investigations. This paper proposes the implementation of a Retrieval Augmented Generation (RAG) LLM, trained with criminology data, to provide swift and actionable insights into specific incidents, thereby enhancing Forensic Data Analysis and facilitating the daily operations of LEAs. © 2024 IEEE.
A5: R0004 | B5: Scopus | C5: 2-s2.0-105048451032 | D5: Ontology-Driven Legal Rule Auditor for Secure, Trustworthy, and Governed RAG Systems | E5: Akremi A. | F5: 2026 | G5: Computers | H5: Article | I5: 10.3390/computers15080471 | M5: Large Language Models (LLMs) have significant potential in regulated domains such as law, healthcare, and compliance, where users need help interpreting complex rules and documents. However, these domains also make the risks of Large Language Models especially serious: a system may hallucinate legal authority, rely on outdated rules, mix jurisdictions, or expose sensitive information. Retrieval-Augmented Generation (RAG) reduces these risks by grounding the model’s answer in a curated document corpus, but standard RAG still does not guarantee that the retrieved sources are legally valid, up to date, applicable to the correct jurisdiction, or safe to use. In this paper, we present an ontology-governed approach to legal RAG. The central idea is to use a legal ontology not merely as background knowledge, but as an active control layer. Before retrieval, the ontology filters legal sources by jurisdiction, topic, lifecycle status, and temporal validity. After generation, validation rules check whether the answer is supported by approved evidence, cites valid legal sources, respects jurisdictional boundaries, and avoids unsafe or privacy-violating content. The system also records retrieval, validation, and response-generation steps in an audit trail to support later review. In this way, the proposed Legal Rule Auditor extends Graph RAG from a retrieval-enhancement technique into a governance architecture for legal question answering. Its goal is not simply to improve answer relevance, but to ensure that answers are legally grounded, trusted, current, jurisdictionally appropriate, and traceable. © 2026 by the author.
A6: R0005 | B6: Scopus | C6: 2-s2.0-105042498808 | D6: Harnessing Large Language Models for Next-Generation Artificial Intelligence Applications | E6: Garg N.; Yangalasetty S.; Vangalapat T.; Kumari M.; Basavaraj M.; Gupta M. | F6: 2026 | G6: 2026 2nd International Conference on Big Data and Machine Learning, ICBDML 2026 | H6: Conference paper | I6: 10.1109/icbdml68582.2026.11545008 | M6: Large Language Models (LLMs) usage is the innovation capable of introducing the new generation of the artificial intelligence system with adaptive thinking, multimodal understanding, and grounded knowledge synthesis. Transformer architecture can be developed; less supervised scalable cognitive automation can be enabled by combining developed augmented retrieval-based generation and parameter-efficient tuning. This paper presents a technically valid and conceptually coherent hybrid-grounded LLM model that has cross-modal embedding alignment, external-knowledge recall, symbolical equivalent validation, and, the hallucination-controlled decoding. The methodology guarantees the semantic integrity and logic-sensitive decision-support in the different fields. The experimental evaluation of a group of complex reasoning demonstrates a considerable improvement as the number of perplexities was decreased to 7.1 instead of 16.8, the level of overall accuracy was increased by 63.4 to 83.8 percent, and the level of F1-score improved by 65.1 to 85.4. Generative metrics also show a significant improvement as BLEU scores 36.9, ROUGE-L scores 56.4 and exact match scores also goes to 63.2 and expectation calibration error also goes down to 3.6 and hallucination error also drops to 5.1. These findings indicate that grounded LLM design is an experimental catalyst of the future AI ecosystems with central interests on reliability, knowledge validity and high-fidelity reason. © 2026 IEEE.
A7: R0006 | B7: Scopus | C7: 2-s2.0-105042194427 | D7: Domain-Specific Legal AI Assistant with Retrieval-Augmented Generation (RAG) | E7: Shahzad K.; Udoh E.; Pryce P.; Ul Haq A. | F7: 2026 | G7: 2026 International Conference on Artificial Intelligence, Systems, and Emerging Technologies, ICAISET 2026 | H7: Conference paper | I7: 10.1109/icaiset66439.2026.11541312 | M7: Large Language Models demonstrate impressive text generation capabilities but suffer from hallucinations and lack jurisdiction-specific grounding when applied to legal domains. This research implements a Retrieval-Augmented Generation system tailored specifically for UK law, combining dense vector retrieval with citation-backed response generation. The system processes legal documents from BAILII and UK legislation, creating a searchable knowledge base through sentence embeddings and FAISS indexing. Evaluation across multiple test queries demonstrates significant improvements over baseline LLM outputs, with hallucination rates reduced from 34.8% to 5.2% and citation accuracy increased to 94.1%. A web-based interface enables users to query the system and upload additional legal documents dynamically. The results validate RAG as an effective approach for building accountable AI systems in high stakes professional domains where accuracy and traceability are essential. © 2026 IEEE.
A8: R0007 | B8: Scopus | C8: 2-s2.0-105037327745 | D8: AI-driven legal argument strength analyzer & counter-argument generator | E8: Harde T.; Jain D.; Patelia K.; Mathur S. | F8: 2026 | G8: Artificial Intelligence and Law | H8: Article | I8: 10.1007/s10506-026-09521-w | M8: Legal argumentation requires sophisticated reasoning, fact analysis, and a subtle appreciation of statutory and case law. The project provides an AI-based framework that uses large language models (LLMs) to aid legal practitioners by creating context-specific counter-arguments, mimicking courtroom-style argumentation, and case outcome simulation. The model is incorporated with a refined GPT-3.5 Turbo model that was trained on expert-curated triplets of case summaries, legal arguments, and counter-arguments from actual court transcripts and legal discussions. To improve factual grounding and minimize hallucinations, the model is supplemented with retrieval-based legal context from statutory law corpora. A new assessment metric—designed with feedback from working attorneys—was proposed to measure the quality of arguments on grounds of persuasiveness, legal appropriateness, and completeness. Quantitative metrics such as cosine similarity and tailored scoring measures demonstrated that AI-generated counter-arguments attained an average similarity of 0.598 with human-written counterparts and were 6.91% more effective at undermining legal claims in terms of final score reduction. Citation metric is used to evaluate the RAG efficiency. The outcome supports the model’s capability to generate coherent, legally sound refutations. Through closely integrating argument generation, evaluation, and a qualitative outcome simulation, this system provides a scalable, explainable method for adversarial legal reasoning. It sets the stage for future applications in legal education, courtroom preparation, and AI-supported decision-making. © The Author(s), under exclusive licence to Springer Nature B.V. 2026.
A9: R0008 | B9: Scopus | C9: 2-s2.0-105022509078 | D9: JURISMIND: Context-Driven Retrieval for Accurate and Relevant Legal Question-Answering in Patent Filings | E9: Prasad P.S.; Trivedi V.; Rao M.; Sen S. | F9: 2025 | G9: International Joint Conference on Knowledge Discovery, Knowledge Engineering and Knowledge Management, IC3K - Proceedings | H9: Conference paper | I9: 10.5220/0013716600004000 | M9: Large Language Models (LLMs) have demonstrated strong performance in domain-specific conversational forums, but they often suffer from hallucinations—producing factually incorrect or contextually irrelevant responses. This issue is particularly critical in the legal domain, where accuracy is paramount. Existing solutions such as fine-tuning and static retrieval methods struggle to handle the complexities of legal language and often fail to provide sufficient contextual grounding. To address this, we propose JURISMIND, a context-driven retrieval-augmented generation (RAG) pipeline designed for the legal domain, with a focus on Patent Filing. Our approach retrieves relevant legal texts, case law, and statutes based on the input query. This retrieved context is combined with a base prompt and the user query, guiding the language model to respond using the provided legal context. This method significantly reduces hallucinations and improves the contextual accuracy of responses. Preliminary evaluation indicates that 56.32% of responses are in strong agreement and 27.59% in fair agreement with ground truth, totaling 83.91% alignment. Furthermore, JURISMIND achieves a BERTScore of 0.91, outperforming the 0.838 BERTScore of a pretrained LLaMA-based model. The code and dataset are publicly released to support adoption and further research in the developer community. Copyright © 2025 by SCITEPRESS – Science and Technology Publications, Lda.
A10: R0009 | B10: Scopus | C10: 2-s2.0-105039609792 | D10: Benchmarking LLM Faithfulness in RAG with Evolving Leaderboards | E10: Tamber M.S.; Bao F.S.; Xu C.; Luo G.; Kazi S.; Bae M.; Li M.; Mendelevitch O.; Qu R.; Lin J. | F10: 2025 | G10: EMNLP 2025 - 2025 Conference on Empirical Methods in Natural Language Processing, Proceedings of the Industry Track | H10: Conference paper | I10: 10.18653/v1/2025.emnlp-industry.54 | M10: Retrieval-augmented generation (RAG) aims to reduce hallucinations by grounding responses in external context, yet large language models (LLMs) still frequently introduce unsupported information or contradictions even when provided with relevant context. This paper presents two complementary efforts at Vectara to measure and benchmark LLM faithfulness in RAG. First, we describe our original hallucination leaderboard, which has tracked hallucination rates for LLMs since 2023 using our HHEM hallucination detection model. Motivated by limitations observed in current hallucination detection methods, we introduce FaithJudge, an LLM-as-a-judge framework that leverages a pool of diverse human-annotated hallucination examples to substantially improve the automated hallucination evaluation of LLMs. We introduce an enhanced hallucination leaderboard centered on FaithJudge that benchmarks LLMs on RAG faithfulness in summarization, question-answering, and data-to-text generation tasks. FaithJudge enables a more reliable benchmarking of LLM hallucinations in RAG and supports the development of more trustworthy generative AI systems: https://github.com/vectara/FaithJudge. © 2025 Association for Computational Linguistics.
A11: R0010 | B11: Scopus | C11: 2-s2.0-105030181042 | D11: Enhanced Multimodal Retrieval Augmented Generation for Cultural Heritage Preservation | E11: Rabeena T.M.; Mohan A. | F11: 2025 | G11: INDISCON 2025 - IEEE 6th India Council International Subsections Conference, Proceedings | H11: Conference paper | I11: 10.1109/indiscon66021.2025.11252350 | M11: Large Language Models (LLMs), which integrate several types of information to facilitate decision-making, have become increasingly sophisticated as a result of recent advances in generative AI. An advanced computational intelligence system known as a Multi-modal Large Language Model (MLLM) is capable of processing and producing responses from a variety of data types, including text, images, audio, and video. Multimodal models integrate multiple modalities to improve understanding and participation, in contrast to traditional LLMs that simply process text. Because of the limited and frozen knowledge scope, advanced MLLMs frequently produce unclear and inaccurate responses, which will make it unsuitable for domain-specific applications. Using the ability of Retrieval Augmented Generation (RAG) to integrate the advantages of generative and statistical retrieval styles makes the LLMs intriguing for use in a variety of fields. It will provide LLMs with comprehensive and current understanding, appropriately expanding the breadth of the information. The fusion of text and images can be done by a multimodal encoder to create a vector embedding repository. The most similar context-rich information from the repository can augment the generation quality of the LLM, thereby eliminating hallucinations and the chances of erroneous data. This multimodal RAG system has a significant impact on domain-specific applications specifically where data are scattered and in different formats. The work uses the repository of different forms of cultural art that enhance societal value by improving access to cultural knowledge, helping to maintain endangered traditions, and promoting global appreciation of heritage. Metrics for different system structure components, such as retrieval performance, multimodal relevance, and pass-modal semantic similarity and alignment, are used to assess the system's efficacy. © 2025 IEEE.
A12: R0011 | B12: Scopus | C12: 2-s2.0-105038112968 | D12: A Multi-Stage Hallucination Reduction Framework for Large Language Models using Retrieval-Augmented Generation and NLI-based Verification | E12: Nag A.; Anusha Bamini A.M.; Brindha D. | F12: 2026 | G12: Proceedings of 6th International Conference on Expert Clouds and Applications, ICOECA 2026 | H12: Conference paper | I12: 10.1109/icoeca68095.2026.11485254 | M12: Strong generative abilities are displayed by Large Language Models (LLMs), but they often generate hallucinations - confident but factually incorrect statements. The safe use of LLMs in academic, legal, medical, and business applications that demand factual reliability is complicated by these hallucinations. This work describes a multi-phase framework for reducing hallucinations that combines a verification module based on Natural Language Inference (NLI) with Retrieval-Augmented Generation (RAG). The system uses a lightweight LLM (Flan-T5) to generate a baseline response, an FAISS-based semantic search mechanism to retrieve supporting evidence, RAG to construct an evidence-grounded response, and an NLI classifier to verify each sentence for factual alignment. Labels that are supported, unsupported, and contradicted are used to calculate a hallucination score. Comparing the suggested system to baseline LLM outputs, experimental results demonstrate a significant improvement in factual accuracy, a decrease in unsupported statements, and an increase in explainability. This work's primary innovation is the combination of retrieval-augmented generation and sentence-level NLI-based verification, which permits quantitative hallucination scoring and validates explainable answers without the need for model fine-tuning. This multi-phase pipeline shows how to construct transparent, reliable, and verifiable AI-driven question-answering systems in a practical manner. © 2026 IEEE.
A13: R0012 | B13: Scopus | C13: 2-s2.0-105029388925 | D13: HIM-RAG: A Heuristic Framework for Iterative Multi-Source Retrieval-Augmented Generation | E13: Li S.; Yu Y.; Yang H.; Zhou Y.; Ji C. | F13: 2025 | G13: Proceedings of the International Joint Conference on Neural Networks | H13: Conference paper | I13: 10.1109/ijcnn64981.2025.11229295 | M13: Large Language Models (LLMs) demonstrate extensive potential in text generation, attracting significant user interest and finding wide applications. However, when faced with insufficient knowledge, LLMs may generate information that deviates significantly from factual accuracy, a phenomenon known as the "hallucination"problem. This issue not only diminishes the practical value of LLMs but also presents significant challenges to their further development. Retrieve-Augmented Generation (RAG) addresses this limitation by incorporating external knowledge retrieval to augment the LLM's knowledge base. However, indiscriminate retrieval can introduce low-quality information, thereby degrading the overall performance of the model. To address these challenges, we propose a novel framework: Heuristic Iterative Multi-source Retrieve-Augmented Generation (HIM-RAG). By leveraging innovative prompt engineering, the framework exploits LLMs' zero-shot reasoning capabilities and their extensive built-in knowledge bases to produce hypothesized understandings and inferences. HIM-RAG incorporates a heuristic iterative retrieval mechanism, employing an extended hybrid knowledge retrieval toolset - such as knowledge graph reasoning chains and web retrieval technologies - coupled with a Critic Language Model (Critic LM) to filter high-quality information highly relevant to the query. This approach enhances the performance of fact-based complex reasoning tasks. Additionally, a re-ranking module evaluates and prioritizes the generated answers from each iteration, selecting the best-quality response and avoiding overgeneration. This ensures the generated content remains highly relevant to user queries. Experiments on open-domain question answering, reasoning, and fact verification tasks demonstrate that the HIM-RAG framework, applied with two LLM variants, exhibits significant advantages in both accuracy and explainability. © 2025 IEEE.
... A18: R0017 | B18: Scopus | C18: 2-s2.0-85197851513 | D18: DIVKNOWQA: Assessing the Reasoning Ability of LLMs via Open-Domain Question Answering over Knowledge Base and Text | E18: Zhao W.; Liu Y.; Niu T.; Wan Y.; Yu P.S.; Joty S.; Zhou Y.; Yavuz S. | F18: 2024 | G18: Findings of the Association for Computational Linguistics: NAACL 2024 - Findings | H18: Conference paper | I18: 10.18653/v1/2024.findings-naacl.5 | M18: Large Language Models (LLMs) excel in generating text but struggle with hallucinations, particularly for uncommon queries, due to reliance on internal knowledge. Retrieval-augmented models address this by integrating external knowledge, enhancing accuracy. Nonetheless, recent approaches have primarily emphasized retrieval from unstructured text corpora, owing to its seamless integration into prompts. When using structured data such as knowledge graphs, most methods simplify it into natural text, neglecting the underlying structures. Moreover, a significant gap in the current landscape is the absence of a realistic benchmark for evaluating the effectiveness of grounding LLMs on heterogeneous knowledge sources (e.g., knowledge base and text). To fill this gap, we have curated a comprehensive dataset that poses two unique challenges: (1) Two-hop multi-source questions that require retrieving information from both open-domain structured and unstructured knowledge sources; retrieving information from structured knowledge sources is a critical component in correctly answering the questions. (2) Generation of symbolic queries (e.g., SPARQL for Wikidata) is a key requirement, which adds another layer of challenge. Our dataset is created using a combination of automatic generation through predefined reasoning chains and human annotation. We also introduce a novel approach that leverages multiple retrieval tools, including text passage retrieval and symbolic language-assisted retrieval. Our model outperforms previous approaches by a significant margin, demonstrating its effectiveness in addressing the above-mentioned reasoning challenges. © 2024 Association for Computational Linguistics.
A19: R0018 | B19: Scopus | C19: 2-s2.0-105026216910 | D19: Retrieval Augmented Generation-Based Large Language Models for Bridging Transportation Cybersecurity Legal Knowledge Gaps | E19: Akbar K.A.; Uddin M.N.; Khan L.; Hockstad T.; Rahman M.; Chowdhury M.; Thuraisingham B. | F19: 2026 | G19: Transportation Research Record | H19: Article | I19: 10.1177/03611981251372471 | J19: 2505.18426 | M19: With the advancement of connected and automated transportation systems, a growing need has emerged for regulatory authorities to update existing laws and statutes, as well as create new ones, to address future implications of connectivity and automation. Specifically, ensuring proper engagement with cybersecurity and data privacy challenges for connected and automated transportation systems will require a comprehensive legal framework at both the federal and state levels. To help policymakers achieve this, a retrieval augmented generation (RAG)-based large language model (LLM) framework, Transportation Cybersecurity and Resiliency (TraCR) AI, has been developed in this study, focusing on extracting pertinent information from existing legislation based on inquiries and crafting LLM-generated responses to highlight potential loopholes for further scrutiny. This study primarily aims to mitigate the hallucinations caused in the domain of LLMs by developing a curated knowledge base of legislative documents and an associated question–answer dataset to improve the effectiveness of query results. This RAG-based framework extracts relevant information to improve the specificity of answers and aids the LLM in providing factually accurate responses with increased reliability. Our analyses reveal that the presented RAG-based framework can aid legislative analysis by generating queries for particular questions and responses. We also compare our RAG framework-generated responses with commercially available LLMs to demonstrate the effectiveness of our approach. TraCR AI outperforms leading commercial LLMs across four distinct metrics, that is, AlignScore, ParaScore, BERTScore, and ROUGE score. This highlights that integrating RAG allows LLMs to produce more factually accurate and up-to-date responses than standalone LLMs. This approach to domain-specific LLM development will improve the quality of legislative analysis that can be used to aid policymakers in meeting the challenge of updating legal codes in accordance with emerging technologies. © The Author(s) 2025
A20: R0019 | B20: Scopus | C20: 2-s2.0-105029874159 | D20: RAG in Specialized Domains: A Survey of QA Chatbots | E20: Rajanidi S.; Anbazhagan M.; Ramya G.R. | F20: 2026 | G20: Lecture Notes in Networks and Systems | H20: Conference paper | I20: 10.1007/978-3-032-15404-0_30 | M20: This paper explores the evolution of large language models (LLMs) and the growing role of retrieval-augmented generation (RAG) systems in overcoming challenges in domain-specific applications. Although LLMs have revolutionized natural language processing (NLP), they face critical limitations in high-stakes domains such as medicine, engineering, and law where accuracy, factuality, and trust are paramount. These shortcomings include hallucinations, outdated knowledge, and vulnerability to adversarial prompts. RAG systems address these issues by integrating LLMs with external domain-specific knowledge sources to improve factual grounding and response reliability. Frameworks like Almanac in clinical settings and KEAG in complex QA tasks demonstrate how RAG reduces hallucinations, enhances interpretability, and delivers accurate, evidence-backed responses. In healthcare, combining LLMs with RAG has raised accuracy from around 93.25% up to 99.25%, showing its impact on real-world decision support. This paper proposes a structured synthesis of advancements, challenges, and optimization strategies in RAG for specialized domains, paving the way for safer, transparent, and adaptive AI systems. © The Author(s), under exclusive license to Springer Nature Switzerland AG 2026.
A21: R0020 | B21: Scopus | C21: 2-s2.0-85214108022 | D21: Generating database schema from requirement specification based on natural language processing and large language model | E21: Salem N.; Hudaib A.; Al-Tarawneh K.; Salem H.; Tareef A.; Salloum H.; Mazzara M. | F21: 2024 | G21: Computer Research and Modeling | H21: Article | I21: 10.20537/2076-7633-2024-16-7-1703-1713 | M21: A Large Language Model (LLM) is an advanced artificial intelligence algorithm that utilizes deep learning methodologies and extensive datasets to process, understand, and generate humanlike text. These models are capable of performing various tasks, such as summarization, content creation, translation, and predictive text generation, making them highly versatile in applications involving natural language understanding. Generative AI, often associated with LLMs, specifically focuses on creating new content, particularly text, by leveraging the capabilities of these models. Developers can harness LLMs to automate complex processes, such as extracting relevant information from system requirement documents and translating them into a structured database schema. This capability has the potential to streamline the database design phase, saving significant time and effort while ensuring that the resulting schema aligns closely with the given requirements. By integrating LLM technology with Natural Language Processing (NLP) techniques, the efficiency and accuracy of generating database schemas based on textual requirement specifications can be significantly enhanced. The proposed tool will utilize these capabilities to read system requirement specifications, which may be provided as text descriptions or as Entity-Relationship Diagrams (ERDs). It will then analyze the input and automatically generate a relational database schema in the form of SQL commands. This innovation eliminates much of the manual effort involved in database design, reduces human errors, and accelerates development timelines. The aim of this work is to provide a tool can be invaluable for software developers, database architects, and organizations aiming to optimize their workflow and align technical deliverables with business requirements seamlessly. © 2024 Nadia Salem, Khawla Al-Tarawneh, Amjad Hudaib, Hamza Salem, Afaf Tareef, Hadi Salloum, Manuel Mazzara.
A22: R0021 | B22: Scopus | C22: 2-s2.0-105040703108 | D22: Grounded in Law: A Multi-Stage Anti-Hallucination Pipeline for Legal RAG Systems in Brazilian Portuguese | E22: Figueiredo A.; Lucas J.; Ribeiro T.; Nery C.; Rios A.; Hebert C.; Florentino L.; Silva A.; Feyerabend Í.; Vidal P.; Cabral B. | F22: 2026 | G22: 17th International Conference on Computational Processing of Portuguese, PROPOR 2026 | H22: Conference paper | M22: Large Language Models (LLMs) are effective text generators but create legal citations at non-trivial rates, a failure mode with serious consequences in legal practice. In Brazilian Portuguese the risk is amplified by citation variability (juridiquês), fragment-level references (article → paragraph → item), and the need to distinguish jurisdictions and court instances. We describe EscavAI, a production Retrieval-Augmented Generation (RAG) system deployed at Escavador, a Brazilian legal-technology platform. The system combines (1) domain-tuned hybrid retrieval (lexical, dense, and cross-encoder reranking) over a large-scale legal corpus; (2) grounded generation with explicit citation constraints; and (3) a post-generation Reference Audit layer that extracts legislation and jurisprudence mentions via specialized taggers, normalizes them to a canonical schema, checks existence against authoritative databases at fragment granularity, verifies fidelity against official texts, and triggers targeted rewrites when inconsistencies are detected. We report production telemetry from 184,895 audited answers containing 43,175 extracted legal references. Legislation references resolve at 81.7%, while jurisprudence references resolve at only 47.1%, identifying case-law normalization as the primary bottleneck for practitioners. Fidelity verification corrected 6.5% of checked answers before delivery, preventing misrepresented legal claims from reaching end users. By converting silent hallucinations into explicit warnings with per-reference status, the system enables legal professionals to trust verified citations and efficiently review flagged ones, rather than manually checking every authority. © 2026 Association for Computational Linguistics.
A23: R0022 | B23: Scopus | C23: 2-s2.0-105025953819 | D23: Evaluating Faithfulness in Agentic RAG Systems for e-Governance Applications Using LLM-Based Judging Frameworks | E23: Papageorgiou G.; Sarlis V.; Maragoudakis M.; Magnisalis I.; Tjortjis C. | F23: 2025 | G23: Big Data and Cognitive Computing | H23: Article | I23: 10.3390/bdcc9120309 | M23: As Large Language Models (LLMs) are core components in Retrieval-Augmented Generation (RAG) systems for knowledge-intensive tasks, concerns regarding hallucinations, redundancy, and unverifiable outputs have intensified, particularly in high-stakes domains, such as e-government. This study proposes a modular, multi-pipeline framework for statement-level faithfulness evaluation for characterizing hallucination and redundancy across both simple and agentic RAG pipelines. Using GPT-4.1, Claude Sonnet-4.0, and Gemini 2.5 Pro as LLM-based judges, this study examines how tool-specific attribution within agentic multi-tool architectures influences the interpretability and traceability of the generated content. By using a modular agentic RAG framework combining symbolic (GraphRAG), semantic (embedding), and real-time (web) retrieval, we benchmark hallucination and redundancy patterns, using state-of-the-art LLM judges. The study examines RAG and agent-based pipelines that attribute outputs to distinct tools, in contrast to traditional single-source RAG systems that rely on aggregated retrieval. Using e-government data sourced from the European Commission’s Press Corner, our evaluation framework assesses not only the frequency, but also the source-aware detectability of hallucinated content. The findings provide actionable insights into how source granularity and retrieval orchestration impact faithfulness evaluation across different pipeline architectures, while also suggesting new directions for explainability-aware RAG design. The study contributes a reproducible, modular framework for automated faithfulness assessment, with implications for transparency, governance compliance, and trustworthy AI deployment. © 2025 by the authors.
A24: R0023 | B24: Scopus | C24: 2-s2.0-105010813331 | D24: CiteVerifier: How Good Are Citation Verifiers and How to Use Them? | E24: Wojtasik K.; Dolega T.; Piasecki M. | F24: 2025 | G24: Lecture Notes in Computer Science | H24: Conference paper | I24: 10.1007/978-3-031-97570-7_19 | M24: Large language models (LLMs) have become powerful tools for understanding documents and answering questions (QA). The grounding of these answers consistently in facts in the given documents may be achieved by citing them in the generated responses. Several approaches to Retrieval Augmented Generation (RAG) have been proposed that incorporate citation to relevant documents to enhance correctness and verifiability. However, evaluation if the document is cited accurately, relies heavily on large generative models for Natural Language Inference. In this work, we evaluate various models in different evaluation schemes for the citation verification task to provide insights into how these models perform and in which evaluation schemes they excel. Our findings show that the TRUE T5 model performs well in verifying the completeness of citations, but struggles when only partial information is available. We also demonstrate that general LLMs can perform citation verification effectively, although the results in citation addition on an already generated answer as post-processing are still suboptimal. We argue that it is important to be mindful of how citation verifiers are used and understand their strengths and limitations. Furthermore, we trained a small and lightweight model, CiteVerifier, which performs exceptionally well despite being magnitudes smaller than other models, making it an ideal solution for low-resource settings. © The Author(s), under exclusive license to Springer Nature Switzerland AG 2025.
A25: R0024 | B25: Scopus | C25: 2-s2.0-85189613527 | D25: Benchmarking Large Language Models in Retrieval-Augmented Generation | E25: Chen J.; Lin H.; Han X.; Sun L. | F25: 2024 | G25: Proceedings of the AAAI Conference on Artificial Intelligence | H25: Conference paper | I25: 10.1609/aaai.v38i16.29728 | M25: Retrieval-Augmented Generation (RAG) is a promising approach for mitigating the hallucination of large language models (LLMs). However, existing research lacks rigorous evaluation of the impact of retrieval-augmented generation on different large language models, which make it challenging to identify the potential bottlenecks in the capabilities of RAG for different LLMs. In this paper, we systematically investigate the impact of Retrieval-Augmented Generation on large language models. We analyze the performance of different large language models in 4 fundamental abilities required for RAG, including noise robustness, negative rejection, information integration, and counterfactual robustness. To this end, we establish Retrieval-Augmented Generation Benchmark (RGB), a new corpus for RAG evaluation in both English and Chinese. RGB divides the instances within the benchmark into 4 separate testbeds based on the aforementioned fundamental abilities required to resolve the case. Then we evaluate 6 representative LLMs on RGB to diagnose the challenges of current LLMs when applying RAG. Evaluation reveals that while LLMs exhibit a certain degree of noise robustness, they still struggle significantly in terms of negative rejection, information integration, and dealing with false information. The aforementioned assessment outcomes indicate that there is still a considerable journey ahead to effectively apply RAG to LLMs. Copyright © 2024, Association for the Advancement of Artificial Intelligence (www.aaai.org). All rights reserved.
A26: R0025 | B26: Scopus | C26: 2-s2.0-105008331529 | D26: Localized Open-Source LLM Aware Retrieval Augmented Generation of Legal Documents: A Case Study on Indian Constitution and Penal Code | E26: Phukon P.; Lokhar Y.; Ray P.P. | F26: 2024 | G26: 2024 IEEE Flagship International BIT Conference: Next Generation Applications in Green Energy Technology, BITCON 2024 | H26: Conference paper | I26: 10.1109/bitcon63716.2024.10985396 | M26: Large Language Models (LLMs) are advanced artificial intelligence systems which are designed to generate human-like language based on their training data. Retrieval- Augmented Generation (RAG) is a framework that enhances the response of LLM by incorporating external information sources, leading to more accurate, context-relevant responses. However, LLMs commonly struggle with contextual relevance, especially in particular fields such as legal documentation, where specific local laws are crucial. Furthermore, there is limited research on the use of RAG technology in the legal area, particularly for producing and analyzing legal documents. This study develops a chatbot using RAG to answer questions on the Indian Constitution (IC) and the Indian Penal Code (IPC), with a Streamlit-based interface to display legal queries and their generated responses. This study analyzes the evaluation of various LLMs integrated with RAG including (including (i) Llama3 8b, (ii) Mistral 7b, (iii) Gemma2 7b, (iv) Phi3 3.8b, and (v) Qwen2 7b and it evaluates their performance in terms of relevance, faithfulness, context recall, and context precision. © 2024 IEEE.
A27: R0026 | B27: Scopus | C27: 2-s2.0-105028582452 | D27: Bridging Legal Knowledge and AI: Retrieval-Augmented Generation with Vector Stores, Knowledge Graphs, and Hierarchical Non-negative Matrix Factorization | E27: Calvin Barron R.; Eren M.; Serafimova O.; Matuszek C.; Alexandrov B. | F27: 2026 | G27: 20th International Conference on Artificial Intelligence and Law, ICAIL 2025 - Proceedings of the Conference | H27: Conference paper | I27: 10.1145/3769126.3769215 | J27: 2502.20364 | M27: Agentic Generative AI, powered by Large Language Models (LLMs) and enhanced with Retrieval-Augmented Generation (RAG), Knowledge Graphs (KGs), and Vector Stores (VSs), represents a transformative technology applicable across specialized domains such as legal systems, research, recommender systems, cybersecurity, and global security, including proliferation research. This technology excels at inferring relationships within vast unstructured or semi-structured datasets. The legal domain we focus on here comprises inherently complex data characterized by extensive, interrelated, and semi-structured knowledge systems with complex relations. It comprises constitutions, statutes, regulations, and case law. Extracting insights and navigating the intricate networks of legal documents and their relations is crucial for effective legal research and decision-making. Here, we introduce a generative AI system, a jurisdiction-specific legal information retrieval that integrates RAG, VS, and KG, constructed via Hierarchical Non-Negative Matrix Factorization (HNMFk), to enhance information retrieval and AI reasoning and minimize hallucinations. In the legal system, these technologies empower AI agents to identify and analyze complex connections among cases, statutes, and legal precedents, uncovering hidden relationships and predicting legal trends - challenging tasks essential for ensuring justice and improving operational efficiency. Our system employs web scraping techniques to systematically collect legal texts, such as statutes, constitutional provisions, and case law, from publicly accessible platforms like Justia. It bridges the gap between traditional keyword-based searches and contextual understanding by leveraging advanced semantic representations, hierarchical relationships, and latent topic discovery. This approach is demonstrated in legal document clustering, summarization, and cross-referencing tasks. The framework marks a significant step toward augmenting legal research with scalable, interpretable, and accurate retrieval methods for semi-structured data, advancing the intersection of computational law and artificial intelligence. © 2025 Copyright held by the owner/author(s).
A28: R0027 | B28: Scopus | C28: 2-s2.0-105033474669 | D28: Reducing Hallucinations in Legal AI: A Retrieval Augmented Generation-Based Model for Accurate Legal Guidance | E28: Gupta S.; Agrawal V.; Negi Y.; Karunanithi S.; Balakrishnan A. | F28: 2026 | G28: IEEE Access | H28: Article | I28: 10.1109/access.2026.3675624 | M28: With the emergence of Large Language Models (LLMs) in the field of Generative Artificial Intelligence (AI), many industries have been significantly transformed, including the legal sector. These models are commonly used for tasks such as summarizing lengthy documents, answering questions, and analyzing large volumes of textual information, which helps improve efficiency in professional settings. However, LLMs are known to generate information that may appear convincing but is not supported by facts, a problem commonly referred to as hallucination. In fields like law, accuracy and reliability are critical. Common LLM errors can have serious consequences. To address this issue, this work proposes a Retrieval-Augmented Generation (RAG)-based approach that incorporates LLMs with a document retrieval mechanism. A custom vector database of 17 recent Indian legal documents sourced from the official Indian government legislation website is built using an embedding model. This database helps find parts of these documents that are relevant to what a user is asking. When the system uses the text it found to answer questions, it is less likely to give information or make up references. The study displays six ways of combining two types of models to see what works best. The combination of Llama2 and all-mpnet-base-v2 turned out to perform the best with a BERTScore F1 of 56.87%. This shows that using legal documents to help answer questions can make the system more reliable. © 2013 IEEE.
A29: R0028 | B29: Scopus | C29: 2-s2.0-85185008870 | D29: Retrieval-based Evaluation for LLMs: A Case Study in Korean Legal QA | E29: Ryu C.; Lee S.; Pang S.; Choi C.; Choi H.; Min M.; Sohn J.-Y. | F29: 2023 | G29: NLLP 2023 - Natural Legal Language Processing Workshop 2023, Proceedings of the Workshop | H29: Conference paper | M29: While large language models (LLMs) have demonstrated significant capabilities in text generation, their utilization in areas requiring domain-specific expertise, such as law, must be approached cautiously. This caution is warranted due to the inherent challenges associated with LLM-generated texts, including the potential presence of factual errors. Motivated by this issue, we propose Eval-RAG, a new evaluation method for LLM-generated texts. Unlike existing methods, Eval-RAG evaluates the validity of generated texts based on the related document that are collected by the retriever. In other words, Eval-RAG adopts the idea of retrieval augmented generation (RAG) for the purpose of evaluation. Our experimental results on Korean Legal Question-Answering (QA) tasks show that conventional LLM-based evaluation methods can be better aligned with Lawyers' evaluations, by combining with Eval-RAG. In addition, our qualitative analysis show that Eval-RAG successfully finds the factual errors in LLM-generated texts, while existing evaluation methods cannot. © 2023 Association for Computational Linguistics.
A30: R0029 | B30: Scopus | C30: 2-s2.0-105031564556 | D30: Challenges for generative AI in legal reasoning | E30: Linna E.; Linna T. | F30: 2026 | G30: Discover Artificial Intelligence | H30: Review | I30: 10.1007/s44163-026-00902-3 | M30: Large Language Models (LLMs) are being integrated into professional domains, yet their limitations in such high-stakes fields as law remain poorly understood. In response, this paper introduces examples of critical challenges to the functioning of generative and other forms of artificial intelligence (AI) as reliable reasoning tools in judicial decision-making. The study deconstructs core requirements and challenges for AI, including the ability to select the correct legal framework across jurisdictions, generate sound arguments based on the doctrine of the sources of law, distinguish ratio decidendi and obiter dicta in case law, resolve ambiguity arising from general clauses like “reasonableness”, manage conflicting legal provisions, and apply the burden of proof correctly. The paper then maps various AI enhancement mechanisms, such as retrieval-augmented generation (RAG), multi-agent systems and neuro-symbolic AI, to these challenges, assessing their potential to bridge the gap between the probabilistic nature of LLMs and the rigorous, choice-driven demands of legal interpretation. Furthermore, the paper sketches a path towards an evaluation framework, proposing that legal requirements be organized into normative, doctrinal, evidential, and technical categories, and subsequently operationalized into domain-specific, testable design obligations. The findings indicate that these techniques can address specific narrow challenges, but they fail to solve the more significant ones that remain, particularly in tasks requiring discretion and transparent, justifiable reasoning. Therefore, we advocate for a staged adoption, first capturing efficiency in simple cases with technology already available today and thereafter sustaining long-term investment in new methods that handle hierarchy, temporality, and other requirements of legally sound reasoning, thus enabling expansion to complex adjudication in the future. © The Author(s) 2026.
A31: R0030 | B31: Scopus | C31: 2-s2.0-105044973052 | D31: Advanced Retrieval-Augmented Generation: Bridging Large Language Models and Knowledge Graphs | E31: Wei W.R.; Wu H. | F31: 2026 | G31: Advanced Retrieval-Augmented Generation: Bridging Large Language Models and Knowledge Graphs | H31: Book | I31: 10.1002/9781394374717 | M31: Build Accurate, Grounded, and Trustworthy AI Systems with Retrieval-Augmented Generation Large language models are powerful-but they hallucinate. Advanced Retrieval-Augmented Generation offers a complete guide from the foundations of information retrieval (IR) to the cutting-edge frontiers of RAG. Bridging large language models (LLMs) and knowledge graphs (KGs), this book provides the theoretical principles, practical techniques, and hands-on frameworks needed to build reliable AI systems that minimize hallucinations and improve factual correctness. The book covers core concepts of Graph-RAG with applications across search, recommendation, and enterprise AI. Practical chapters demonstrate implementations using LlamaIndex, Neo4j, and leading Graph-RAG frameworks. Readers will learn: * IR and LLM fundamentals - model paradigms, transformer architecture, model families, training techniques, prompt engineering, applications, and limitations * RAG pipeline engineering - chunking, indexing, retrieval, ranking, and generation * KG construction and analytics - schema design, extraction techniques, graph algorithms, embeddings, and GNNs * Graph-RAG architectures and evaluation - graph-based retrieval, graph-assisted generation, hybrid LLM-KG workflows, frameworks, benchmarks, and metrics * Emerging directions - multimodal KGs, dynamic graphs, explainable RAG, RL-based traversal, and enterprise-scale implementations With extensive hands-on examples and production-ready patterns, Advanced Retrieval-Augmented Generation is an indispensable resource for AI practitioners, ML engineers, researchers, and architects building the next generation of reliable, knowledge-grounded AI systems. © 2026 by The Institute of Electrical and Electronics Engineers, Inc. All rights reserved.
A32: R0031 | B32: Scopus | C32: 2-s2.0-105021966122 | D32: RadOncRAG: A Novel Retrieval-Augmented Generation Framework Improves Large Language Model Benchmark Performance in Radiation Oncology | E32: Thaker N.G.; Redjal N.; Dicker A.; Loaiza-Bonilla A.; Royce T.; Subbiah V.; Deendyal V.; Gabriel J.R.; Shetty N.; Choudhri A.; Thaker G.H. | F32: 2025 | G32: JCO Clinical Cancer Informatics | H32: Article | I32: 10.1200/cci-25-00220 | M32: PURPOSE – Large language models (LLMs) show promise in assisting knowledge-intensive fields such as oncology, where up-to-date information and multidisciplinary expertise are critical. Traditional LLMs risk hallucinations and reliance on static, possibly outdated data that lack domain-specific context. Retrieval-augmented generation (RAG) has emerged as a strategy to address these issues by incorporating domain-specific information from external knowledge repositories.METHODS – We evaluated 15 LLMs, including Meta Llama-2/3, generative pretrained transformer (GPT)-3.5/4/4o variants, Claude-3, Gemini-2.0, and DeepSeek-R1. In a zero-shot workflow, each LLM answered 298 scorable questions from the 2021 American College of Radiology in-training examination. We implemented a RAG pipeline (Iridium Model) that transforms user prompts into vector embeddings, queries a specialized radiation oncology database, and merges relevant text with the original prompt to form an augmented query. We compared zero-shot versus RAG-augmented performance.RESULTS – Larger-parameter LLMs had higher zero-shot accuracy, with six models outscoring graduating residents (P < .01). Top scorers were reasoning models GPT-4o1, o3-mini, and DeepSeek-R1, which achieved 91.6%, 86.6%, and 91.6% without RAG, respectively. Gemini-2.0 improved 6.7% (to 79.2%), Llama-3-70b 8.4% (to 75.8%), and GPT-4o 5.7% (to 85.6%) with RAG. Top scoring reasoning models surpassed graduating resident averages by 17.7%-20% (P < .01), but had no improvement or detriment with RAG. Domain-specific gains occurred in clinical, biology, and physics. Majority voting boosted aggregate accuracy when individual model performance exceeded 50%. RAG workflows and reasoning models incurred higher computational costs.CONCLUSION – Radiation-oncology–specific retrieval-augmented generation pipeline enhances nonreasoning LLM performance in radiation oncology by integrating domain-specific evidence, whereas it does not improve performance of reasoning models. These findings demonstrate that RAG can elevate clinical decision support by enabling simpler, cost-effective nonreasoning models to tackle complex tasks through retrieval capabilities—an efficient alternative to extensive model training that also yields citable, evidence-based explanations. © 2025 American Society of Clinical Oncology
A33: R0032 | B33: Scopus | C33: 2-s2.0-105020013806 | D33: Contract Pre-Review Assistance System Based on RAG and LLM | E33: Wang C.-H.; Yang X.-S.; Liu J.-Y.; Liu Y.-J. | F33: 2025 | G33: Lecture Notes in Networks and Systems | H33: Conference paper | I33: 10.1007/978-981-96-6438-2_25 | M33: Contract review is a common challenge for governments, businesses, and individuals. It becomes challenging when manual reviews are slow, legal expertise is lacking, and clauses are complex. These issues often lead to legal disputes and business conflicts. Traditional rule-based contract review tools often struggle with ambiguous language and unstructured content. Large language models (LLM) can quickly analyze contracts and find risks. But, they are unreliable due to “hallucinations” and a lack of knowledge of rare clauses. This study used retrieval-augmented generation (RAG) technology to overcome these challenges. It integrated verified legal data with large language models. This improved review accuracy to 93.67%. The F1-scores reached 91.95% for compliant clauses and 94.79% for non-compliant ones. The ROC-AUC metric improved to 0.93. The results show that this approach works. It improves the classification and risk identification of contract clauses. It also helps in contract review in the legal and business sectors, promoting the use of legal tech. © The Author(s), under exclusive license to Springer Nature Singapore Pte Ltd. 2025.
A34: R0033 | B34: Scopus | C34: 2-s2.0-105034269880 | D34: Leveraging LLMs to Build a Semi-Synthetic Dataset for Legal Information Retrieval: a Case Study on the Italian Civil Code and GPT4-o | E34: Proietti M.; Passaro L.; Lenci A. | F34: 2025 | G34: CEUR Workshop Proceedings | H34: Conference paper | M34: Although raw textual data in the legal domain is abundant, making it easy to collect large amounts of material from several sources, structured and annotated data needed to fine-tune machine learning models is limited and difficult to obtain. Creating human-annotated datasets is both time- and money-consuming, which often makes impractical to get quality data to train machines on various legal language tasks. AI models such as Large Language Models (LLMs) are becoming appealing to generate synthetic data, judge model responses, and annotate textual information, so to cope with such shortcomings. In this work, we wish to evaluate the applicability of LLMs for the automatic generation of a dataset of legal query-passage pairs to train retrieval systems. Indeed, Legal Information Retrieval (LIR) has been crucial for the creation of robust search systems for legal documents and is now gaining new importance in the context of the Retrieval Augmented Generation (RAG) framework, which is becoming a widespread tool to cope with LLMs hallucinating behaviours. Our goal is to test the feasibility of building a query-passage dataset in which the queries are generated by an LLM about real textual passages and assess the reliability of such a process in terms of the generation of hallucination-free data points in a delicate domain, as the legal one. We do so in a two-step pipeline spelt out as follows: i) we use the Italian Civil Code as a source of self-contained, semantically coherent legal textual passages and ask the model to generate hypothetical questions on them; ii) we use the LLM itself to judge the coherence of the questions to spot those inconsistent with the passage. We then select a random subset of the question-passage pairs and ask humans to evaluate them. Finally, we compare human and model evaluations on the randomly selected subset. We show that the model generates many questions easily, and while it lags behind humans when evaluating the appropriateness of the generated questions with respect to the reference passages in zero-shot settings, it substantially reduces the gap with human judgements when only two examples are provided. © 2025 Copyright for this paper by its authors.
A35: R0034 | B35: Scopus | C35: 2-s2.0-85206333493 | D35: Automating Systematic Literature Reviews with Retrieval-Augmented Generation: A Comprehensive Overview | E35: Han B.; Susnjak T.; Mathrani A. | F35: 2024 | G35: Applied Sciences (Switzerland) | H35: Article | I35: 10.3390/app14199103 | M35: This study examines Retrieval-Augmented Generation (RAG) in large language models (LLMs) and their significant application for undertaking systematic literature reviews (SLRs). RAG-based LLMs can potentially automate tasks like data extraction, summarization, and trend identification. However, while LLMs are exceptionally proficient in generating human-like text and interpreting complex linguistic nuances, their dependence on static, pre-trained knowledge can result in inaccuracies and hallucinations. RAG mitigates these limitations by integrating LLMs’ generative capabilities with the precision of real-time information retrieval. We review in detail the three key processes of the RAG framework—retrieval, augmentation, and generation. We then discuss applications of RAG-based LLMs to SLR automation and highlight future research topics, including integration of domain-specific LLMs, multimodal data processing and generation, and utilization of multiple retrieval sources. We propose a framework of RAG-based LLMs for automating SRLs, which covers four stages of SLR process: literature search, literature screening, data extraction, and information synthesis. Future research aims to optimize the interaction between LLM selection, training strategies, RAG techniques, and prompt engineering to implement the proposed framework, with particular emphasis on the retrieval of information from individual scientific papers and the integration of these data to produce outputs addressing various aspects such as current status, existing gaps, and emerging trends. © 2024 by the authors.
A36: R0035 | B36: Scopus | C36: 2-s2.0-105043221651 | D36: AI-Oriented KM Implementation Paradigm in Enterprise—RAG | E36: Wu Q. | F36: 2026 | G36: Generative Artificial Intelligence in Knowledge Management Systems: Concepts, Design, and Case Studies | H36: Book chapter | I36: 10.4324/9781003640929-7 | M36: With the rapid development of artificial intelligence (AI) technology, large language models (LLMs) have been widely applied in various enterprise scenarios due to their powerful text-generation capabilities. However, as practical usage deepens, the limitations of LLMs have gradually emerged, including knowledge hallucination, insufficient reasoning ability, and imprecise information, making them unable to meet enterprises’ high demands for accuracy and reliability. Against this backdrop, the retrieval-augmented generation (RAG) paradigm has emerged. By integrating external knowledge bases with large models, RAG significantly reduces knowledge hallucination, improves the accuracy of generated content, and provides a new solution for enterprise knowledge management implementation. © 2026 selection and editorial matter, Gang Liu, Jin Chen, and Eric Tsui.
A37: R0036 | B37: Scopus | C37: 2-s2.0-105046119552 | D37: Harnessing Retrieval-Augmented Generation for Legal Document Analysis and Case Law Prediction: A Case Study on Enhancing Transparency and Efficiency in Legal NLP | E37: Malini A.; Thippa S.; Pai T.V. | F37: 2026 | G37: Retrieval Augmented Generation for Natural Language Processing | H37: Book chapter | I37: 10.1002/9781394336128.ch14 | M37: As the need for accuracy and efficiency in analyzing legal information increases, this case study examines the application of retrieval-augmented generation (RAG) systems in legal practice. Legal workflows are document-centric; however, the massive amounts and complexity of contracts, statutes, and case law are significant barriers to both traditional analytics and the newer natural language processing (NLP) tools. The powerful generative capabilities of large language models (LLMs) in legal practice are limited because of the possibilities of inaccuracies, being outdated, confidential information, and lack of explainability, all of which are covered in current research and best practice guidance on legal NLP. This study explored RAG as a strong model for grounding LLM output based on legitimate legal documents. By permitting artificial intelligence (AI) systems to retrieve, contextualize, and synthesize language from limited yet curated legally relevant corpora, e.g., firm-specific case files versus statutory code or contracts, RAG elevates the concept of probabilistic text generation to evidence-based legal reasoning. This analysis is concerned with (i) the function of RAG for automating high-volume contract review and (ii) case law prediction as an example of real change for legal strategy and operational effectivenes. The findings suggest that RAG reduced the time taken to carry out legal research and document review and added greater transparency and traceability to insights produced by AI that evidenced the high ethical, benchmarking, and professional standards that define legal services. Most importantly, using RAG on private infrastructures reduces the client data risks that arise from the use of public LLMs. These findings demonstrated that RAG provided a better and sustainable solution for law firms to use the analytical capabilities of LLMs and have three clear advantages regarding domain accuracy, explainability, and client trust. © 2026 Scrivener Publishing LLC.
A38: R0037 | B38: Scopus | C38: 2-s2.0-105031137565 | D38: Precedent Aware Legal Reasoning System for Turkish Jurisdiction with RAG Supported LLMs | E38: Genç U.; Keskin O.F.; Akman N.P.; Berkol A.; Birant D. | F38: 2025 | G38: ISMSIT 2025 - 9th International Symposium on Multidisciplinary Studies and Innovative Technologies, Proceedings | H38: Conference paper | I38: 10.1109/ismsit67332.2025.11267996 | M38: Large Language Models have achieved impressive progress in natural language processing, yet their tendency to hallucinate undermines reliability in high-stakes domains such as law. This paper presents a precedent-grounded Retrieval-Augmented Generation framework for legal question answering in the Turkish judicial system. The framework integrates dense retrieval with domain-tuned embeddings and sparse retrieval with BM25 and introduced two domain-adapted models: LexiTurk111M for retrieval and LexiTurk-14B for generation. Compared to strong baselines, the system delivers clear gains in retrieval accuracy, answer correctness, and faithfulness, while substantially reducing hallucinations. In particular, LexiTurk14B outperforms its base Qwen3-14B, with correctness increasing from 2.10 to 3.10 in closed-book and 4.23 with RAG. These results highlight the effectiveness of precedent-grounded RAG and establish a reproducible path toward explainable and trustworthy legal AI in under-resourced languages. © 2025 IEEE.
A39: R0038 | B39: Scopus | C39: 2-s2.0-105029641358 | D39: From vectors to knowledge graphs: A comprehensive analysis of modern retrieval-augmented generation architectures | E39: Kamalipour A.A.; Asadi S.; Amiri Chimeh M.M. | F39: 2026 | G39: Computer Science Review | H39: Article | I39: 10.1016/j.cosrev.2026.100925 | M39: Large Language Models (LLMs) suffer from hallucination, a systemic weakness that erodes trust by producing confident but factually incorrect content, especially in high-stakes settings. Retrieval-Augmented Generation (RAG) directly addresses this limitation by tightly coupling generation to verifiable, up-to-date evidence. This comprehensive survey introduces a unified four-stage taxonomy of Indexing, Retrieval, Fusion, and Generation that deconstructs modern RAG architectures and provides a common lens for comparing systems. Drawing on more than 300 references, we analyze the full spectrum from foundational Vector RAG to the multi-hop reasoning capabilities of Graph RAG, and we chart emerging paradigms such as Agentic RAG, Multimodal RAG, Hybrid RAG, and reasoning-centric variants. Beyond architectural taxonomies, we provide a deep implementation-oriented treatment of indexing and similarity search, including a practical comparison of leading vector databases and graph databases for real-world deployments. We further present a comprehensive benchmark comparison that unifies evaluation datasets and metrics for both vector- and graph-based pipelines, and we consolidate trade-offs across representative RAG strategies in a comparison of key approaches. Together, these contributions position RAG as a mature design pattern for building grounded, auditable AI systems and offer practitioners, graduate students, and researchers a structured roadmap from basic pipelines to advanced, evidence-based reasoning systems. © 2026 Elsevier Inc.
A40: R0039 | B40: Scopus | C40: 2-s2.0-105040296859 | D40: Technical and Ethical Perspectives on Building Intelligent Legal Assistants With LLM and RAG Pipelines: Building a Legal Chatbot With LLMs and RAG | E40: Mbounkap J.; Djigo H.; Masheh T.; Nzooh A.; Kar A. | F40: 2026 | G40: AI Transformations in Global Legal Systems | H40: Book chapter | I40: 10.4018/979-8-3373-7685-1.ch013 | M40: The rapid advancement of Large Language Models (LLMs) has opened new possibilities for intelligent legal assistants that support research, drafting, case analysis, and decision preparation. This article presents how LLMs combined with Retrieval-Augmented Generation (RAG) can power context aware and reliable legal AI systems. The article outlines technical foundations of such assistants, describing how RAG pipelines integrate legal documents to produce outputs based on reliable sources and reduce hallucinations. Key technical challenges such as constructing legal knowledge bases and managing computational demands are also discussed. Beyond technical design, the article explores the ethical implications of deploying legal chatbots, including bias, unequal access, accountability, and overreliance on automated interpretations. We highlight the requirements for responsible AI in these chatbots, covering explainability, human oversight, and compliance. The article defines a roadmap for developing legal assistants that are accurate, transparent, and aligned with legal and societal norms. Copyright © 2026 by IGI Global Scientific Publishing. All rights reserved. No part of this publication may be reproduced, stored or distributed in any form or by any means, electronic or mechanical, including photocopying, without written permission from the publisher. Use of this publication to train generative artificial intelligence (AI) technologies is expressly prohibited. The publisher reserves all rights to license its use for generative AI training and machine learning model development.
A41: R0040 | B41: Scopus | C41: 2-s2.0-105011587485 | D41: Adapting Large Language Models to Vietnamese Law: Pretrained LLM Refinement vs Retrieval Augmented Generation | E41: Nguyen N.P.; Le T.V.Q.; Le A.-C.; Nguyen V.-H.; Nguyen V.-C. | F41: 2024 | G41: Proceedings - International Conference on Knowledge and Systems Engineering, KSE | H41: Conference paper | I41: 10.1109/kse63888.2024.11063566 | M41: Large Language Models (LLMs) have shown their potential in a wide range of tasks, but much of their development has been concentrated on the English language. This focus has created a noticeable gap in the availability of LLMs for other languages, as well as in specialized domains such as legal contexts. In this study, we aim to address this gap by developing a Vietnamese Large Language Model and building a Retrieval-Augmented Generation (RAG) system within legal settings. Our methodology includes building and processing legal datasets, followed by training the LLM specifically for Vietnamese legal applications. Our findings suggest that both the LLM and the RAG system perform well in retaining legal knowledge and providing more reliable answers to legal inquiries. These results highlight the potential of these approaches for legal tasks in the Vietnamese language. This research not only contributes to the application of AI in the legal field but also offers important insights into the development of AI solutions for non-English languages, addressing a critical gap in current AI research and supporting more inclusive language model applications. © 2024 IEEE.
A42: R0041 | B42: Scopus | C42: 2-s2.0-105000626125 | D42: Smart E-learning Development Tool Using Generative AI and Retrieval-Augmented Approach | E42: Goswami T.; Bhavana G.; Anirudh C.V.S.; Reddy L.; Ram Mohan Rao K. | F42: 2025 | G42: Lecture Notes in Computer Science | H42: Conference paper | I42: 10.1007/978-3-031-81821-9_24 | M42: Generative AI is a technology that uses data to produce something new in response to a prompt entered by a human. Large Language Models (LLM) is a type of generative AI, the latest language model that can understand and interpret natural language. LLMs are very large deep-learning models which are pre-trained on huge amounts of existing data. LLMs can be used for text generation, code generation, translation, summarization, conversational AI and chatbots. With the advent of the latest technologies, one of the challenges faced in LLM is that the model pre-trained may become obsolete in future. The Retrieval Augmented Generation (RAG) technique is helpful in such cases as it augments the existing data as an external source and can be integrated with the pre-trained LLM. The paper uses Generative AI using LLM and RAG for the development of smart e-learning course content in the field of learning science to assist subject matter experts (SME) or instruction designers. The tool simplifies presenting complex information without compromising accuracy. The SME finds it easy to balance content creation with their other professional responsibilities. The scope of the paper is to generate content consisting of course objectives, course outcomes, and questionnaires for assessment. The course content thus generated in a certain required format is assessed by the subject matter expert to fine-tune. © The Author(s), under exclusive license to Springer Nature Switzerland AG 2025.
A43: R0042 | B43: Scopus | C43: 2-s2.0-105051750458 | D43: Large language models in the patent lifecycle: A systematic review | E43: Jiang P.; Arena A.P.; Sorce S.; Atherton M. | F43: 2026 | G43: World Patent Information | H43: Article | I43: 10.1016/j.wpi.2026.102506 | M43: Patents constitute the world's largest repository of codified technical knowledge, yet their length, legal terminology, and linguistic ambiguity have limited the effectiveness of traditional text mining and keyword-based retrieval. Large Language Models (LLMs) offer new capabilities for processing this complexity, but the resulting literature is fragmented across disciplines, with no comprehensive synthesis of how these tools are being applied across the patent lifecycle. This study systematically reviews the literature on LLMs and Generative AI in patent analytics, following the PRISMA 2020 protocol, to map current applications, characterise dominant architectural trends, and identify priority research gaps. Using Scopus and Web of Science, we identified and screened a corpus of 129 peer-reviewed studies published from 2018 to early 2026, organised according to three patent lifecycle stages: creation and pre-filing (N = 36), examination and prosecution (N = 34), and post-grant management (N = 60). The review shows that research activity has grown sharply since 2024, accompanied by a shift from exploratory, single-task studies toward applied, multi-component systems. Across this literature, Retrieval-Augmented Generation (RAG) has become the dominant architectural response to hallucination risk, grounding generated content in verified external sources. The review further identifies persistent gaps in domain-specific evaluation metrics, multimodal reasoning, and governance frameworks for AI-generated patent content. For patent professionals and institutions, the findings indicate that LLMs are best positioned as assistive tools requiring human oversight rather than autonomous replacements, and that the central challenge going forward is not whether but how the patent system governs this transition. © 2026 The Authors.
A44: R0043 | B44: Scopus | C44: 2-s2.0-85209663384 | D44: InLegalLLaMA: Indian Legal Knowledge Enhanced Large Language Model | E44: Ghosh S.; Verma D.; Ganesan B.; Bindal P.; Kumar V.; Bhatnagar V. | F44: 2024 | G44: CEUR Workshop Proceedings | H44: Conference paper | M44: Large Language Models (LLM) are being increasingly used in many domains including legal and justice. General purpose models trained on web data are not performant enough on legal text analytics (LTA) tasks while fine tuning task specific models is expensive because of the annotation and compute costs. Pre-training domain or application specific models is increasingly popular. However pre-training LLMs in small domain corpora like Indian legal documents and judgements is challenging. We introduce our InLegalLLaMA model, along with the related training corpus, adapted for the Indian legal domain, that shows promise of improved performance on LTA tasks. We also propose a RAG-based framework for petition drafting that benefits from the legal language generation and reasoning abilities of large language models. © 2024 Copyright for this paper by its authors.
A45: R0044 | B45: Scopus | C45: 2-s2.0-105045715491 | D45: ClauseRoute: Risk-aware clause-guided routing for retrieval-augmented legal reasoning | E45: Du Z.; Wu C.; Lu J.; Gao Y.; Chen M. | F45: 2027 | G45: Expert Systems with Applications | H45: Article | I45: 10.1016/j.eswa.2026.133633 | M45: Retrieval-augmented generation has demonstrated effectiveness in mitigating hallucinations in large language models by grounding generation in external knowledge. Despite its promise, however, reasoning-intensive legal tasks remain challenging due to two fundamental challenges: a substantial semantic gap between colloquial natural language queries and formally structured statutory provisions, and the degradation of reasoning performance in long-context settings caused by the well-known lost-in-the-middle phenomenon. To address these challenges, we propose ClauseRoute, a clause-guided retrieval-augmented generation strategy that uses legal draft clauses as intermediate anchors to steer retrieval in the legal domain. Instead of relying on direct answer generation, ClauseRoute adapts a 1.5B language model to the target domain through supervised fine-tuning and reinforcement learning on domain-specific data, enabling the lightweight LLM to generate draft clauses that resemble formal statutory language. By reformulating complex legal reasoning as a constrained, clause-focused semantic selection process, this design improves inference efficiency while suppressing biases inherent in open-ended text generation. ClauseRoute further incorporates a risk-aware routing mechanism to mitigate attention degradation in long-context legal reasoning. By computing cross-channel consistency between dense and sparse retrieval signals, the strategy dynamically activates a mapping, filtering, and reasoning module that reorganizes long contexts and ensures that critical legal provisions remain within the effective attention region of the model. Extensive experiments on four representative benchmarks show that ClauseRoute consistently outperforms existing methods, effectively mitigating the semantic gap and long-context degradation in legal reasoning across models of varying scales. The code is available at https://github.com/d001121/ClauseRoute.git. © 2026 Elsevier Ltd. All rights are reserved, including those for text and data mining, AI training, and similar technologies.
A46: R0045 | B46: Scopus | C46: 2-s2.0-105027122345 | D46: HyPA-RAG: A Hybrid Parameter Adaptive Retrieval-Augmented Generation System for AI Legal and Policy Applications | E46: Kalra R.; Wu Z.; Gulley A.; Hilliard A.; Guan X.; Koshiyama A.; Treleaven P. | F46: 2025 | G46: Proceedings of the 2025 Annual Conference of the Nations of the Americas Chapter of the Association for Computational Linguistics: Human Language Technologies: Long Papers, NAACL-HLT 2025 | H46: Conference paper | I46: 10.18653/v1/2025.naacl-industry.79 | M46: Large Language Models (LLMs) face limitations in AI legal and policy applications due to outdated knowledge, hallucinations, and poor reasoning in complex contexts. Retrieval-Augmented Generation (RAG) systems address these issues by incorporating external knowledge, but suffer from retrieval errors, ineffective context integration, and high operational costs. This paper presents the Hybrid Parameter-Adaptive RAG (HyPA-RAG) system, designed for the AI legal domain, with NYC Local Law 144 (LL144) as the test case. HyPA-RAG integrates a query complexity classifier for adaptive parameter tuning, a hybrid retrieval approach combining dense, sparse, and knowledge graph methods, and a comprehensive evaluation framework with tailored question types and metrics. Testing on LL144 demonstrates that HyPA-RAG enhances retrieval accuracy, response fidelity, and contextual precision, offering a robust and adaptable solution for high-stakes legal and policy applications. © 2025 Association for Computational Linguistics.
A47: R0046 | B47: Scopus | C47: 2-s2.0-105038381823 | D47: Automated Machine Learning to Enhance Knowledge Retrieval in Retrieval-Augmented Generation Pipelines | E47: Magnini M.; Aguzzi G.; Sanna L.; Magnolini S.; Bellan P.; Dragoni M.; Montagna S. | F47: 2026 | G47: Communications in Computer and Information Science | H47: Conference paper | I47: 10.1007/978-3-032-16708-8_34 | M47: The emergence of Large Language Models (LLMs) has introduced exciting possibilities for applications in the digital health domain. However, their unpredictable nature necessitates the development of trustworthy strategies to prevent the generation of hallucinations. A common approach to address this challenge is using Retrieval-Augmented Generation (RAG), where text generation is supported by controlled knowledge injected into the prompts. Even with RAG, ensuring reliable and authoritative information generation requires further research. In a previous work, we presented an enhanced approach to the classic RAG pipeline, introducing an initial step where the LLM generates an enhanced query to support the retrieval step. Results showed that performances are highly sensitive to the techniques adopted for embedding queries and retrieving documents. Accordingly, in this paper, we experiment with a novel automated machine-learning approach to conduct extensive testing across various configurations and explore the retrieval module. Our findings highlight that the embedder and, especially, the retrieval strategies strongly impact the overall performance of the RAG pipeline. © The Author(s), under exclusive license to Springer Nature Switzerland AG 2026.
A48: R0047 | B48: Scopus | C48: 2-s2.0-105042089719 | D48: Hybrid Retrieval Augmented Generation: Reliable and Accurate Question Answering | E48: Dalali Y.; Zeguendry A.; Aaroui A. | F48: 2026 | G48: 2nd International Conference on Global Aeronautical Engineering and Satellite Technology, GAST 2026 - Proceeding | H48: Conference paper | I48: 10.1109/gast67799.2026.11523296 | M48: Retrieval Augmented Generation (RAG) systems address the well-known limitations of large language models (LLMs),namely knowledge staleness and factual hallucination, by grounding generation in dynamically retrieved documents. Single-modality dense retrieval, however, systematically fails on queries requiring precise keyword matching, such as error codes, product identifiers, or regulatory references. This paper presents a modular, reproducible hybrid RAG pipeline that combines FAISS-based dense retrieval with BM25 lexical search and a Cross-Encoder reranking step, orchestrated through an explicit LangGraph state machine. Using efficient CPU-friendly models (all-MiniLM-L6-v2 for embeddings and ms-marco-MiniLM-L-6-v2 for reranking), the system demonstrates that architectural sophistication can substitute for raw model scale. Evaluation on a 2,000-sample subset of the HotpotQA distractor benchmark shows that the full pipeline raises nDCG from 0.652 (vector-only baseline) to 0.790 (Hybrid+Rerank), a statistically significant improvement (t = -24.29, p < 10-114). Hallucination rate, assessed with an automated LLM judge, drops from 0.20 to 0.40 grounding score (higher is better). A complete reproducibility package, including source code, data injection scripts, and cached indices,is provided so that all reported results can be independently verified with a single command. © 2026 IEEE.
A49: R0048 | B49: Scopus | C49: 2-s2.0-105010261957 | D49: AUTO-GDA: AUTOMATIC DOMAIN ADAPTATION FOR GROUNDING VERIFICATION IN RETRIEVAL-AUGMENTED GENERATION | E49: Leemann T.; Petridis P.; Vietri G.; Manousakas D.; Roth A.; Aydöre S. | F49: 2025 | G49: 13th International Conference on Learning Representations, ICLR 2025 | H49: Conference paper | M49: While retrieval-augmented generation (RAG) has been shown to enhance factuality of large language model (LLM) outputs, LLMs still suffer from hallucination, generating incorrect or irrelevant information. A common detection strategy involves prompting the LLM again to assess whether its response is grounded in the retrieved evidence, but this approach is costly. Alternatively, lightweight natural language inference (NLI) models for efficient grounding verification can be used at inference time. While existing pre-trained NLI models offer potential solutions, their performance remains subpar compared to larger models on realistic RAG inputs. RAG inputs are more complex than most datasets used for training NLI models and have characteristics specific to the underlying knowledge base, requiring adaptation of the NLI models to a specific target domain. Additionally, the lack of labeled instances in the target domain makes supervised domain adaptation, e.g., through fine-tuning, infeasible. To address these challenges, we introduce Automatic Generative Domain Adaptation (Auto-GDA). Our framework enables unsupervised domain adaptation through synthetic data generation. Unlike previous methods that rely on handcrafted filtering and augmentation strategies, Auto-GDA employs an iterative process to continuously improve the quality of generated samples using weak labels from less efficient teacher models and discrete optimization to select the most promising augmented samples. Experimental results demonstrate the effectiveness of our approach, with models fine-tuned on synthetic data using Auto-GDA surpassing the performance of the teacher model and reaching the performance level of LLMs at 10 % of their computational cost. © 2025 13th International Conference on Learning Representations, ICLR 2025. All rights reserved.
A50: R0049 | B50: Scopus | C50: 2-s2.0-105031890958 | D50: Optimization of Limtations and Reduction of Hallucination in Llm Using Rag: A Performancedriven Framework | E50: Dhande S.; Shinde S.; Shitole M.; Dhakane S.; Zope Y.; Tambe P. | F50: 2025 | G50: 2025 9th International Conference on Computing, Communication, Control and Automation, ICCCBEA 2025 | H50: Conference paper | I50: 10.1109/iccubea65967.2025.11283777 | M50: Large Language Models (LLMs) have revolutionized natural language processing but still struggle with reliability issues, notably generating plausible yet incorrect information, or hallucinations. This paper introduces a Retrieval-Augmented Generation (RAG) framework designed to address these shortcomings by combining generative models with retrieval-based methods. The framework uses domain-specific datasets, effective text chunking, and advanced embedding techniques to dynamically integrate external knowledge, influencing the factual accuracy, coherence, and relevancy of the generated content. By incorporating Maximum Marginal Relevance (MMR), the system achieved a 15% improvement in overall retrieval accuracy and a 20% boost in context precision compared to baseline models. Evaluations across several metrics-including context precision, recall, entity recall, and relevancedemonstrated significant gains in accuracy and a notable reduction in hallucination rates. These promising results shows the potential of RAG architectures which can improve the reliability and productiveness of LLMs, offering a strong foundation for future advancements and broader applications across various domains. © 2025 IEEE.
A51: R0050 | B51: Scopus | C51: 2-s2.0-105017007925 | D51: Retrieval-Augmented Generation vs. Baseline LLMs: A Multi-Metric Evaluation for Knowledge-Intensive Content | E51: Vinayan Kozhipuram A.; Shailendra S.; Kadel R. | F51: 2025 | G51: Information (Switzerland) | H51: Article | I51: 10.3390/info16090766 | M51: (1) Background: The development of Generative Artificial Intelligence (GenAI) is transforming knowledge-intensive domains such as Education. However, Large Language Models (LLMs), which serve as the foundational components for GenAI tools, are trained on static datasets, often producing misleading, factually incorrect, or outdated responses. Our study explores the performance gains of Retrieval-Augmented LLMs over baseline LLMs while also identifying the trade-off opportunity between smaller-parameter LLMs augmented with user-specific data to larger parameter LLMs. (2) Methods: We experimented with four different LLMs, each with a different number of parameters, to generate outputs. These outputs were then evaluated across seven lexical and semantic metrics to identify performance trends in Retrieval-Augmented Generation (RAG)-Augmented LLMs and analyze the impact of parameter size on LLM performance. (3) Results and Discussions: We have synthesized 968 different combinations to identify this trend with the help of different LLM sizes/parameters: TinyLlama 1.1B, Mistral 7B, Llama 3.1 8B, and Llama 1 13 B. These studies were grouped into two themes: RAG-Augmented LLM percentage improvements to baseline LLMs and compelling trade-off possibilities of RAG-Augmented smaller-parameter LLMs to larger-parameter LLMs. Our experiments show that RAG-Augmented LLMs demonstrate high lexical and semantic scores relative to baseline LLMs. This offers RAG-Augmented LLMs as a compelling trade-off for reducing the number of parameters in LLMs and lowering overall resource demands. (4) Conclusions: The findings outline that by leveraging RAG-Augmented LLMs, smaller-parameter LLMs can perform better or equivalently to large-parameter LLMs, particularly demonstrating strong lexical improvements. They reduce the risks of hallucination and keep the output more contextualized, making them a better choice for knowledge-intensive content in academic and research sectors. © 2025 by the authors.
A52: R0051 | B52: Scopus | C52: 2-s2.0-105020027384 | D52: ”A Midsummer Night’s Dream” quest for truth: From ChatGPT “hallucinations” to RAG reasoning and ACURAI precision — a scoping review on detection, minimizing, and (almost) complete error elimination and enhancing Large Language Modelsʹ reliability | E52: Anghelescu A.; Munteanu C.; Anghelescu L.A.-M.; Onose G. | F52: 2025 | G52: Balneo and PRM Research Journal | H52: Article | I52: 10.12680/balneo.2025.847 | M52: Like A Midsummer Night’s Dream, large language models (LLMs) exhibit vast imagination, drawing on massive training datasets. However, they may fabricate or mix information, lacking mechanisms to verify real‐world sources. Most commercial LLMs, including those used in medicine, remain prone to hallucinations—plausible but false content. Retrieval‐Augmented Generation (RAG) aims to address this by grounding LLM outputs in real‐time access to verified sources like scientific databases. A 2023–2025 PubMed search identified 91 papers on RAG and LLM applications across biomedical domains; 78 were useful for our paper, adressing medical domains. RAG techniques significantly reduce hallucinations by ensuring that only validated information informs model outputs. ACURAI, an advanced system based on “phrase dominance and discrete functional units (DFUs),” further enhances LLM accuracy. Tested on a novel “RAG‐Truth Dataset Caveats,” ACURAI eliminated 91–100% of junk outputs in GPT‐3.5 and GPT‐4. While LLMs can resemble Puck (creative yet unreliable), ACURAI, aided by RAG, acts more like Theseus, grounding answers in verified data. This framework strengthens the possible role of LLMs in clinical diagnosis, academic writing, and patient education, offering a practical path toward safer and more accurate medical AI. Ultimately, human oversight remains key to interpreting and validating AI‐generated outputs. © 2025 by the authors.
A53: R0052 | B53: Scopus | C53: 2-s2.0-105003723162 | D53: Hallucination-Free? Assessing the Reliability of Leading AI Legal Research Tools | E53: Magesh V.; Surani F.; Dahl M.; Suzgun M.; Manning C.D.; Ho D.E. | F53: 2025 | G53: Journal of Empirical Legal Studies | H53: Article | I53: 10.1111/jels.12413 | M53: Legal practice has witnessed a sharp rise in products incorporating artificial intelligence (AI). Such tools are designed to assist with a wide range of core legal tasks, from search and summarization of caselaw to document drafting. However, the large language models used in these tools are prone to “hallucinate,” or make up false information, making their use risky in high-stakes domains. Recently, certain legal research providers have touted methods such as retrieval-augmented generation (RAG) as “eliminating” or “avoid[ing]” hallucinations, or guaranteeing “hallucination-free” legal citations. Because of the closed nature of these systems, systematically assessing these claims is challenging. In this article, we design and report on the first preregistered empirical evaluation of AI-driven legal research tools. We demonstrate that the providers' claims are overstated. While hallucinations are reduced relative to general-purpose chatbots (GPT-4), we find that the AI research tools made by LexisNexis (Lexis+ AI) and Thomson Reuters (Westlaw AI-Assisted Research and Ask Practical Law AI) each hallucinate between 17% and 33% of the time. We also document substantial differences between systems in responsiveness and accuracy. Our article makes four key contributions. It is the first to assess and report the performance of RAG-based proprietary legal AI tools. Second, it introduces a comprehensive, preregistered dataset for identifying and understanding vulnerabilities in these systems. Third, it proposes a clear typology for differentiating between hallucinations and accurate legal responses. Last, it provides evidence to inform the responsibilities of legal professionals in supervising and verifying AI outputs, which remains a central open question for the responsible integration of AI into law. © 2025 The Author(s). Journal of Empirical Legal Studies published by Cornell Law School and Wiley Periodicals LLC.
A54: R0053 | B54: Scopus | C54: 2-s2.0-105001920424 | D54: A Reasoning-Focused Legal Retrieval Benchmark | E54: Zheng L.; Guha N.; Arifov J.; Zhang S.; Skreta M.; Manning C.D.; Henderson P.; Ho D.E. | F54: 2025 | G54: CS and LAW 2025 - Proceedings of the 2025 Symposium on Computer Science and Law | H54: Conference paper | I54: 10.1145/3709025.3712219 | M54: As the legal community increasingly examines the use of large language models (LLMs) for various legal applications, legal AI developers have turned to retrieval-augmented LLMs (“RAG” systems) to improve system performance and robustness. An obstacle to the development of specialized RAG systems is the lack of realistic legal RAG benchmarks which capture the complexity of both legal retrieval and downstream legal question-answering. To address this, we introduce two novel legal RAG benchmarks: Bar Exam QA and Housing Statute QA. Our tasks correspond to real-world legal research tasks, and were produced through annotation processes which resemble legal research. We describe the construction of these benchmarks and the performance of existing retriever pipelines. Our results suggest that legal RAG remains a challenging application, thus motivating future research. © 2025 Copyright held by the owner/author(s).
A55: R0054 | B55: Scopus | C55: 2-s2.0-105046177060 | D55: Application of Retrieval-Augmented Generation Technology in Chatbot Development | E55: Rajković P.; Stojiljković N. | F55: 2026 | G55: 2026 49th MIPRO ICT and Electronics Convention, MIPRO 2026 - Proceedings | H55: Conference paper | I55: 10.1109/mipro70003.2026.11591817 | M55: Large language models (LLMs) made a significant step forward and demonstrated substantial progress across general chat platforms and intelligent assistants. However, their deployment in domain-specific applications is somewhat behind in terms of response quality due to static knowledge boundaries, substantial programming requirements for adaptation, and the potential to generate hallucinated responses. This paper addresses the problem by implementing the Retrieval-Augmented Generation (RAG) approach and adapting it to serve as a suitable general-purpose help module. Developed system further emphasizes the generation process by supplying the model with appropriate background information retrieved from a semantically indexed knowledge base. As a result, the model's responses are grounded in concrete, domain-specific sources instead of depending solely on internal model parameters. As a result, the model's responses are grounded in concrete, domain-specific sources, with response times suitable for interactive technical support scenarios and reduced hallucination frequency. © 2026 IEEE.
A56: R0055 | B56: Scopus | C56: 2-s2.0-85215531476 | D56: RAG for Question-Answering for Vocal Training Based on Domain Knowledge Base | E56: Leung C.-H.J.; Yi Y.; Kuai L.; Li Z.; Yeung S.-K.A.; Lee K.-W.J.; Ho K.-H.K.; Hung K. | F56: 2024 | G56: Proceedings of the 2024 11th IEEE International Conference on Behavioural and Social Computing, BESC 2024 | H56: Conference paper | I56: 10.1109/besc64747.2024.10780718 | M56: Although Large language models (LLMs) are well-known due to their superior capacity for text generation and logical inference, they are found to be inaccurate in domain-specific question-answering tasks. The powerful generator still tends to generate content even when the LLM does not have sufficient knowledge at all, which is known as the hallucination problem. We find there is a research void in applying LLMs in the vocal training industry, which requires intensive expert knowledge in any chatbot or intelligent tutor services. This paper details employing Retrieval-Augmented Generation (RAG) technology to develop a domain-specific language model, addressing inherent challenges such as hallucination, where large models generate plausible but inaccurate content, and lack of domain specificity. By segmenting the knowledge base and establishing semantic similarities between user queries and knowledge data, the project lays a solid foundation for integrating RAG, significantly improving response accuracy and contextual relevance. The report highlights the successful implementation of RAG, enhancing system intelligence and personalization for user-specific needs, discusses challenges and solutions during the implementation process, and outlines future directions to expand RAG capabilities and improve user experiences. © 2024 IEEE.
A57: R0056 | B57: Scopus | C57: 2-s2.0-105040340713 | D57: Small Language Model Adaptation to the Italian Agricultural Legal Domain | E57: Pelosi M.; Ghosh R.C.; Cirillo E.; Amato A.; Ciano C. | F57: 2026 | G57: Lecture Notes on Data Engineering and Communications Technologies | H57: Book chapter | I57: 10.1007/978-3-032-23335-6_19 | M57: The application of generative AI in highly regulated and specialized areas, such as Italian agricultural law, is associated with a number of challenges related to data confidentiality, domain specificity, and hallucinations. In order to address these challenges, we designed a Retrieval-Augmented Generation (RAG) model that is strictly grounded in authoritative legislative sources. The proposed system uses a hybrid dense-sparse retrieval approach on a curated corpus of Italian legislative texts, carefully segmented at the article level. The performance of two compact models, Gemma and Granite, was tested using a dataset of real-world legal questions obtained from professional exams, with a focus on legal grounding. The experimental results show that, when combined with accurate retrieval, Small Language Models (SLMs) are able to provide reliable and contextually grounded legal reasoning. These results highlight both the feasibility and the current limitations of using small-scale models for domain-specific LegalAI applications in civil law systems. © The Author(s), under exclusive license to Springer Nature Switzerland AG 2026.
A58: R0057 | B58: Scopus | C58: 2-s2.0-105052111287 | D58: A Hybrid Agentic RAG Architecture for Legal Decision Support: Integrating Utility-Based Reasoning with LLM-Orchestrated Retrieval | E58: Nair D.A.; Bang S.; Abhyankar K. | F58: 2026 | G58: 2026 International Conference on Trends in Quantum Computing and Emerging Business Technologies, TQCEBT 2026 | H58: Conference paper | I58: 10.1109/tqcebt67648.2026.11681462 | M58: The present paper explains a hybrid variety of an Agentic Retrieval- Augmented Generation (RAG) model, the model that results in goal-oriented and utility-oriented agentic reasoning in legal guidance. It purports to seek to study family law cases with large-scale language models (e.g. GPT-4, Claude 3, Gemini 1.5, DeepSeek-R1) on the basis of modular retrieval systems (vector stores, graph databases, relational DBs) and post-hoc bias and factuality. This agent is dynamically deciding what to do which can be retrieval, critique, reformulation etc but this choice depends on a parametrized utility that considers the accuracy, neutrality and latency of responding. The qualitative research is simulated legal consultation to which we apply simulated grounded Maharashtra based case law and thematic biases. The results show that the verifiability of the responses (through citation) and hallucinations are greater and lesser respectively in the two sexes and also that there exists no difference in how law is framed. This schema is biased to multistage reasoning and self-correction which has become the default of agentic AI and constitutional alignment. The journal is institutionalizing a field-specific reproducible architecture that entails the introduction of ideals of equity throughout AI decision pipelines into sensitive areas such as justice systems. © 2026 IEEE.
A59: R0058 | B59: Scopus | C59: 2-s2.0-105043871923 | D59: Application of large language models in legal queries: experiments with the artificial intelligence for legal assistance challenge | E59: Martín C.A.; Torres J.M.; Aguilar R.M.; Bacallado M.A.; Alayón S. | F59: 2026 | G59: Logic Journal of the IGPL | H59: Article | I59: 10.1093/jigpal/jzag043 | M59: This study evaluates the applicability of generative artificial intelligence (AI), specifically Large Language Models (LLMs), in legal assistance tasks using the Artificial Intelligence for Legal Assistance challenge dataset, which includes 197 statutes, 2914 judicial cases, and 50 legal queries. The research compared conversational LLM tools with semantic retrieval systems based on dense embeddings. Results show that general-purpose tools (ChatGPT, NotebookLM) achieved poor discrimination, while embedding-based methods significantly improved accuracy: the OpenAI text-embedding-ada-002 model reached 46.43% retrieval accuracy, and a fine-tuned all-mpnet-base-v2 model improved from 18.9% to 31.87% (a 68.6% relative gain). These findings demonstrate that combining LLMs with semantic retrieval techniques enhances precision and scalability in legal information systems, offering a viable roadmap for developing domain-specific, efficient, and sustainable AI legal assistants. © The Author(s) 2026. Published by Oxford University Press. This is an Open Access article distributed under the terms of the Creative Commons Attribution License (https://creativecommons.org/licenses/by/4.0/), which permits unrestricted reuse, distribution, and reproduction in any medium, provided the original work is properly cited.
A60: R0059 | B60: Scopus | C60: 2-s2.0-85199415229 | D60: A Survey on RAG Meeting LLMs: Towards Retrieval-Augmented Large Language Models | E60: Fan W.; Ding Y.; Ning L.; Wang S.; Li H.; Yin D.; Chua T.-S.; Li Q. | F60: 2024 | G60: Proceedings of the ACM SIGKDD International Conference on Knowledge Discovery and Data Mining | H60: Conference paper | I60: 10.1145/3637528.3671470 | M60: As one of the most advanced techniques in AI, Retrieval-Augmented Generation (RAG) can offer reliable and up-to-date external knowledge, providing huge convenience for numerous tasks. Particularly in the era of AI-Generated Content (AIGC), the powerful capacity of retrieval in providing additional knowledge enables RAG to assist existing generative AI in producing high-quality outputs. Recently, Large Language Models (LLMs) have demonstrated revolutionary abilities in language understanding and generation, while still facing inherent limitations such as hallucinations and out-of-date internal knowledge. Given the powerful abilities of RAG in providing the latest and helpful auxiliary information, Retrieval-Augmented Large Language Models (RA-LLMs) have emerged to harness external and authoritative knowledge bases, rather than solely relying on the model's internal knowledge, to augment the quality of the generated content of LLMs. In this survey, we comprehensively review existing research studies in RA-LLMs, covering three primary technical perspectives: Furthermore, to deliver deeper insights, we discuss current limitations and several promising directions for future research. Updated information about this survey can be found at: https://advanced-recommender-systems.github.io/RAG-Meets-LLMs/ © 2024 Copyright held by the owner/author(s). Publication rights licensed to ACM.
A61: R0060 | B61: Scopus | C61: 2-s2.0-105033678661 | D61: Generation and Visualization of BPMN from Legal Documents | E61: Wilsen W.; Dewandaru A.; Candra M.Z.C. | F61: 2025 | G61: Proceedings of 2025 IEEE International Conference on Data and Software Engineering, ICoDSE 2025 | H61: Conference paper | I61: 10.1109/icodse68111.2025.11351687 | M61: Legal documents play a critical role in defining organizational processes, yet their complexity often hinders the derivation of accurate process models. Recent advances in Large Language Models (LLMs) provide an opportunity to automate this task through enhanced natural language understanding and generation. This study presents an LLM-based framework for generating and visualizing Business Process Model and Notation (BPMN) diagrams from legal texts. The proposed architecture integrates Retrieval-Augmented Generation (RAG) to address token limitations while ensuring actor-aware and scalable workflow generation. Experimental evaluation on Indonesian General Election Law (UU Pemilu No. 7/2017) and the Criminal Procedure Law (KUHAP, UU No. 8/1981) shows that the GPTbased approach outperforms Gemini, achieving over 92 % in accuracy, precision, and recall, with significantly reduced processing time. The key contribution lies in bridging legal text and BPMN workflows through an LLM-driven pipeline. Current limitations include handling complex conditional gateways, while future work will focus on enhancing reasoning for conditional flows and optimizing the BPMN engine layout so that diagram dimensions (width and height) dynamically adjust to the generated text, thereby improving readability and usability. © 2025 IEEE.
... A82: R0081 | B82: Scopus | C82: 2-s2.0-105013956512 | D82: EvidenceBot: A Privacy-Preserving, Customizable RAG-Based Tool for Enhancing Large Language Model Interactions | E82: Khan N.I.; Filkov V. | F82: 2025 | G82: Proceedings of the ACM SIGSOFT Symposium on the Foundations of Software Engineering | H82: Conference paper | I82: 10.1145/3696630.3728607 | M82: Large Language Models (LLMs) have become pivotal in reshaping the world by enabling advanced natural language processing tasks such as document analysis, content generation, and conversational assistance. Their ability to process and generate human-like text has unlocked unprecedented opportunities across different domains such as healthcare, education, finance, and more. However, commercial LLM platforms face several limitations, including data privacy concerns, context size restrictions, lack of parameter configurability, and limited evaluation capabilities. These shortcomings hinder their effectiveness, particularly in scenarios involving sensitive information, large-scale document analysis, or the need for customized output. This underscores the need for a tool that combines the power of LLMs with enhanced privacy, flexibility, and usability. To address these challenges, we present EvidenceBot, a local, Retrieval-Augmented Generation (RAG)-based solution designed to overcome the limitations of commercial LLM platforms. EvidenceBot enables secure and efficient processing of large document sets through its privacy-preserving RAG pipeline, which extracts and appends only the most relevant text chunks as context for queries. The tool allows users to experiment with hyperparameter configurations, optimizing model responses for specific tasks, and includes an evaluation module to assess LLM performance against ground truths using semantic and similarity-based metrics. By offering enhanced privacy, customization, and evaluation capabilities, EvidenceBot bridges critical gaps in the LLM ecosystem, providing a versatile resource for individuals and organizations seeking to leverage LLMs effectively. © 2025 Copyright held by the owner/author(s).
A83: R0082 | B83: Scopus | C83: 2-s2.0-105040143954 | D83: Measuring Faithfulness and Abstention: An Automated Pipeline for Evaluating LLM-Generated 3-ply Case-Based Legal Arguments | E83: Zhang L.; Gray M.; Savelka J.; Ashley K.D. | F83: 2025 | G83: CEUR Workshop Proceedings | H83: Conference paper | M83: Large Language Models (LLMs) demonstrate potential in complex legal tasks like argument generation, yet their reliability remains a concern. Building upon pilot work assessing LLM generation of 3-ply legal arguments using human evaluation, this paper introduces an automated pipeline to evaluate LLM performance on this task, specifically focusing on faithfulness (absence of hallucination), factor utilization, and appropriate abstention. We define hallucination as the generation of factors not present in the input case materials and abstention as the model’s ability to refrain from generating arguments when instructed and no factual basis exists. Our automated method employs an external LLM to extract factors from generated arguments and compares them against the ground-truth factors provided in the input case triples (current case and two precedent cases). We evaluated eight distinct LLMs on three tests of increasing difficulty: 1) generating a standard 3-ply argument, 2) generating an argument with swapped precedent roles, and 3) recognizing the impossibility of argument generation due to lack of shared factors and abstaining. Our findings indicate that while current LLMs achieve high accuracy (over 90%) in avoiding hallucination on viable argument generation tests (Tests 1 & 2), they often fail to utilize the full set of relevant factors present in the cases. Critically, on the abstention test (Test 3), most models failed to follow instructions to stop, instead generating spurious arguments despite the lack of common factors. This automated pipeline provides a scalable method for assessing these crucial LLM behaviors, highlighting the need for improvements in factor utilization and robust abstention capabilities before reliable deployment in legal settings. Project page: Link. © 2025 Copyright for this paper by its authors.
A84: R0083 | B84: Scopus | C84: 2-s2.0-85163821488 | D84: Gracenote.ai: Legal Generative AI for Regulatory Compliance | E84: Ioannidis J.; Harper J.; Quah M.S.; Hunter D. | F84: 2023 | G84: CEUR Workshop Proceedings | H84: Conference paper | M84: We investigate the transformative potential of large language models (LLMs) in the legal and regulatory compliance domain by developing advanced generative AI solutions, including a horizon scanning tool, an obligations generation tool, and an LLM-based expert system. Our approach combines the LangChain framework, OpenAI's GPT-4, text embeddings, and prompt engineering techniques to effectively reduce hallucinations and generate reliable and accurate domain-specific outputs. A human-in-the-loop control mechanism is used as a final backstop to ensure accuracy and mitigate risk. Our findings emphasise the role of LLMs as foundation engines in specialist tools and lay the groundwork for building the next generation of legal and compliance applications. Future research will focus on extending support across multiple jurisdictions and languages, refining prompts and text embedding datasets for enhanced legal reasoning capabilities, and developing autonomous AI agents and robust LLM-based expert systems. © 2023 Copyright for this paper by its authors. Use permitted under Creative Commons License Attribution 4.0 International (CC BY 4.0).
A85: R0084 | B85: Scopus | C85: 2-s2.0-105027366800 | D85: Elevating Legal LLM Responses: Harnessing Trainable Logical Structures and Semantic Knowledge with Legal Reasoning | E85: Yao R.; Wu Y.; Wang C.; Xiong J.; Wang F.; Liu X. | F85: 2025 | G85: Proceedings of the 2025 Annual Conference of the Nations of the Americas Chapter of the Association for Computational Linguistics: Human Language Technologies: Long Papers, NAACL-HLT 2025 | H85: Conference paper | I85: 10.18653/v1/2025.naacl-long.290 | M85: Large Language Models (LLMs) have achieved impressive results across numerous domains, yet they experience notable deficiencies in legal question-answering tasks. LLMs often generate generalized responses that lack the logical specificity required for expert legal advice and are prone to hallucination, providing answers that appear correct but are unreliable. Retrieval-Augmented Generation (RAG) techniques offer partial solutions to address this challenge, but existing approaches typically focus only on semantic similarity, neglecting the logical structure essential to legal reasoning. In this paper, we propose the Logical-Semantic Integration Model (LSIM), a novel supervised framework that bridges semantic and logical coherence. LSIM comprises three components: reinforcement learning predicts a structured fact-rule chain for each question, a trainable Deep Structured Semantic Model (DSSM) retrieves the most relevant candidate questions by integrating semantic and logical features, and in-context learning generates the final answer using the retrieved content. Our experiments on a real-world legal QA dataset-validated through both automated metrics and human evaluation-demonstrate that LSIM significantly enhances accuracy and reliability compared to existing methods. © 2025 Association for Computational Linguistics.
A86: R0085 | B86: Scopus | C86: 2-s2.0-105030324122 | D86: Explainable Knowledge Access: Recursive and Rerank-Based RAG for Interpretable QA | E86: Cosseddu M.; Giuliani A.; Manca M.M.; Pilloni M.; Podda A.S.; Tiddia S.G. | F86: 2026 | G86: Communications in Computer and Information Science | H86: Conference paper | I86: 10.1007/978-3-032-15638-9_13 | M86: In response to the crucial need for more transparent and reliable tools based on Large Language Models (LLMs), this work introduces a novel and explainable architectural enhancement to the Retrieval-Augmented Generation (RAG) pipeline. As organizations increasingly rely on LLMs to navigate and interpret vast, unstructured datasets, ensuring the factual accuracy and traceability of generated content has become essential. Our key contribution is designing a system that formally anchors all produced output in a formally verified knowledge base, thereby significantly alleviating challenges related to hallucination and verbosity. This focus on transparency is achieved by providing exact citations to the information used, enabling users to trace the source of generated content. Our work demonstrates significant improvements to chunk retrieval accuracy, achieved using a multi-granularity recursive chunking strategy and re-ranking with maximum information exposure to the LLM. We also provide extensive comparative analysis of various combinations of LLM and embedding models under this enhanced system. Our contributions lay the groundwork for developing more responsible and reliable AI solutions across knowledge-intensive domains, focusing on enhanced information retrieval and transparent response generation. © The Author(s), under exclusive license to Springer Nature Switzerland AG 2026.
A87: R0086 | B87: Scopus | C87: 2-s2.0-105009411848 | D87: RAG Powered LLMs for QA: Evolution, Challenges, Applications, and Future Directions | E87: Zeeshan H.M.A.; Faizan M.; Zia U.; Gohar A. | F87: 2025 | G87: 2025 International Conference on Communication Technologies, ComTech 2025 | H87: Conference paper | I87: 10.1109/comtech65062.2025.11034531 | M87: Large language models (LLMs) are evolving to excel in challenging tasks such as text generation, mathematical reasoning, code generation, question answering, text summarization, etc. However, the responses generated by LLMs are prone to hallucinations, out-of-the-date knowledge, and nontransparent and untraceable reasoning. Retrieval augmented generation (RAG) addresses these shortcomings by incorporating external knowledge in the LLM prompt. RAG combines parametric knowledge of LLM with non-parametric knowledge from external databases by efficient retrieval techniques. This comprehensive review paper provides a detailed overview of the significance and emergence of RAG. Moreover, the building blocks of RAG are thoroughly discussed along with the evolution, challenges, and current research trends of deploying RAG-based applications. Finally, we explore the RAG performance enhancement strategies while also underlining the potential future research directions. © 2025 IEEE.
A88: R0087 | B88: Scopus | C88: 2-s2.0-105040643102 | D88: Legal-AP: A Framework to Enhance LLM’s Legal Reasoning via Knowledge Augmentation and Adapter-Wise Parametric Fusion | E88: Chang A.; Chen Y.; Liu K.; Zhao J. | F88: 2026 | G88: Lecture Notes in Computer Science | H88: Conference paper | I88: 10.1007/978-981-92-0369-7_20 | M88: Legal AI tasks require large language models (LLMs) to demonstrate robust legal reasoning for complex, knowledge-intensive, and multi-task scenarios such as legal judgment prediction (LJP), statute article generation (SAG), and legal document generation (LDG). However, the field’s emphasis on logical consistency, coupled with persistent hallucination issues, limits the practicality of conventional retrieval-augmented generation (RAG), which struggles with lengthy legal texts, limited context windows, and high computational costs. To address these challenges, we propose Legal-AP, a framework that enhances multi-task legal performance and reasoning quality through knowledge Augmentation and adapter-wise Parametric fusion. Instead of appending retrieved documents to the input, Legal-AP injects external legal knowledge and reasoning-critical patterns directly into model parameters via Low-Rank Adaptation (LoRA). Multiple task-specific adapters are dynamically composed to enable efficient, domain-aware reasoning across diverse legal tasks. Furthermore, we construct Legal-CA, a multi-task dataset covering criminal, administrative, and civil domains, with expert annotations emphasizing both substantive legal and reasoning aspects. Experiments show that Legal-AP consistently surpasses conventional RAG approaches and achieves comparable or superior performance to GPT-4o on several tasks, underscoring the promise of parametric knowledge integration for advancing reasoning-driven Legal AI. © The Author(s), under exclusive license to Springer Nature Singapore Pte Ltd. 2026.
A89: R0088 | B89: Scopus | C89: 2-s2.0-105011250589 | D89: GraphRAG Makes it Possible to Digest Convoluted Legal Jargon | E89: Ngangmeni J.; Rawat D.B. | F89: 2025 | G89: Proceedings - 2025 IEEE Conference on Artificial Intelligence, CAI 2025 | H89: Conference paper | I89: 10.1109/cai64502.2025.00268 | M89: Legal jargon easily overwhelms those who lack proper training. Aspiring entrepreneurs may feel intimidated by the complex web of regulations between them and their goals. Even when available, crucial information can be extensive and difficult to navigate without costly professional help. This article leverages recent advancements in the field of Natural Language Processing (NLP) to investigate the potential of Large Language Models (LLMs) in helping stakeholders understand the legal requirements of business aspirations. Inspired by [7], we compare 2 Machine Learning (ML) retrieval methods-Retrieval Augmented Generation (RAG), and Graph Retrieval Augmented Generation (GraphRAG)-assessing their performance on 2 sets of LLM generated queries. More specifically, our study evaluates 6 sub-models-4 from Light Retrieval Augmented Generation (LightRAG) and 2 from Microsoft's Graph Retrieval Augmented Generation (MGRAG). We examine these sub-models across 4 key criteria-comprehensiveness, diversity, empowerment, and directness-as well as a combination of all 4 which we call 'over-all'. After 3 separate experiments, we observe that GraphRAGs have a clear advantage over RAGs for digesting complex language in this task. Within GraphRAGs, we observe that MGRAG has a slight advantage over LightRAG and naive RAG. We present the results in grouped bar charts to offer clear and accessible comparisons, enabling anyone interested to quickly make informed decisions about which methods best suit their business needs. © 2025 IEEE.
A90: R0089 | B90: Scopus | C90: 2-s2.0-105049647587 | D90: Leveraging Retrieval-Augmented Generation to Support Legal Question Answering: Evidence from Indonesian Human Trafficking Court Decisions | E90: Wicaksono G.W.; Hidayah N.P.; Aditya C.S.K.; Anwar M.H.F.; Anhari N.A.; Dewa A.F.P.; Fatikasari H.; Insani M.A.P. | F90: 2026 | G90: International Journal on Informatics Visualization | H90: Article | I90: 10.62527/joiv.10.4.4760 | M90: The exponential growth of court decisions in Indonesia has posed a crucial challenge for legal practitioners in obtaining relevant information. Conventional search systems fail to capture the in-depth legal context, while Large Language Models (LLMs) are prone to producing hallucinations that can mislead legal reasoning. This study proposes and tests the implementation of Retrieval-Augmented Generation (RAG) to support Legal Question Answering LLM-based Quality Assurance (LQA) to improve factual accuracy. This study used 408 Indonesian court decisions related to criminal cases. Human trafficking data collected and standardized from 143 district courts. The RAG framework is designed in three stages: indexing, search, and incremental generation. We evaluated three Open-source LLM models: Gemma, LLaMA, and Qwen. Three models are also combined with two retrieval methods: BM25 (lexical) and Dense (semantics). Experimental results show that Qwen 3, especially when combined with BM25 RAG, consistently produces the highest overall answer quality across all evaluation metrics (ROUGE and BLEU). The BM25 method is significantly more effective than dense retrieval. Due to the highly standardized nature of court decision documents, Qwen demonstrated peak performance on structured information categories such as “identitas_terdakwa”, achieving a ROUGE-L score of 0.899. The primary contribution of this study is demonstrating that RAG significantly reduces the risk of LLM hallucinations in a legal context. However, error analysis suggests that future improvements should focus on strengthening generation controls to address these issues: unsupported generation and remaining model-rejection behavior. © 2026, Politeknik Negeri Padang. All rights reserved.
A91: R0090 | B91: Scopus | C91: 2-s2.0-105031145657 | D91: Retrieval Augmented Generation (RAG) using LLMs | E91: Vahaj M.; Raza S.M.; Nehra V. | F91: 2025 | G91: Annual International Conference on Data Science, Machine Learning and Blockchain Technology, AICDMB 2025 | H91: Conference paper | I91: 10.1109/aicdmb64359.2025.11277692 | M91: Large Language Models (LLMs) have transformed AI with their ability to generate human-like text, but challenges such as hallucinations, outdated knowledge, and contextual inaccuracies persist. Retrieval-Augmented Generation (RAG) systems address these limitations by integrating real-time information retrieval with LLMs, enhancing the accuracy, relevance, and trustworthiness of generated content. This research aims to develop and evaluate RAG systems to improve the reliability of AI-generated outputs. To assess the impact of RAG, a comparative analysis is conducted on LLMs, including Llama, Mistral, Falcon, and T5. Performance has been evaluated by comparing results on similar tasks with and without RAG, focusing on metrics such as accuracy, contextual understanding, and domain-specific relevance. The findings demonstrate that RAG significantly enhances content generation, resolving critical challenges associated with LLMs. This study underlines the potential of retrieval-augmented techniques to improve the reliability and applicability of AI-generated content across various domains. ©2025 IEEE.
A92: R0091 | B92: Scopus | C92: 2-s2.0-105040522292 | D92: Leveraging LLMs and RAG for AI-Driven Legal Assistance | E92: Lekhana A.; Suresh R.; Pramath K.P.; Prabhudas R.; Srivastava S. | F92: 2026 | G92: Lecture Notes in Networks and Systems | H92: Conference paper | I92: 10.1007/978-3-032-23219-9_13 | M92: The adoption of Large Language Models (LLMs) and Generative AI is changing a multitude of industries, including the legal sector. The practice of law traditionally relies on experience, extensive study and nuanced judgment. As AI grows exponentially, it leads to more human-like interactions and improved efficiency by automating routine tasks like contract drafting and legal documentation. This paper introduces AgentLegal, a state-of-the-art Retrieval-Augmented Generation (RAG) based LLM tailored for corporate legal applications, with the main focus on Indian law. AgentLegal assists corporate lawyers with its numerous features which includes contract drafting, strategic guidance in corporate takeovers, sentiment analysis, real-time user feedback, and risk assessment, while also simplifying complex legal jargon. Developed using Python, Streamlit for UI, Mistral AI: all-MiniLM-L12-v2 as the LLM model and Pinecone as the vector database, AgentLegal is a significant step forward in the advancement in legal technology. While existing AI tools focus narrowly on tasks like case comprehension or contract review, AgentLegal provides a consolidated view of legalities across all domains of Indian Law. It achieves a BLEU score of 0.3655, reflecting moderate lexical similarity. ROUGE scores (Recall: 0.3773, Precision: 0.1739) indicate that the content is considered effective with scope for accuracy improvement. A BERT Score F1 of 0.0378 highlights initial semantic alignment and contextual relevance. This paper evaluates its architecture, capabilities, and potential to enhance efficiency and decision-making for corporate legal practitioners. © The Author(s), under exclusive license to Springer Nature Switzerland AG 2026.
A93: R0092 | B93: Scopus | C93: 2-s2.0-105032503338 | D93: A Survey of Retrieval-Augmented Generation (RAG) for Large Language Models | E93: Ma Y.; Nie H.; Chen C.; Zhang J.; Jiang J.; Wang B.; Xia Y. | F93: 2025 | G93: Proceedings - 2025 International Conference on Trustworthy Big Data and Artificial Intelligence, ICTBAI 2025 | H93: Conference paper | I93: 10.1109/ictbai68361.2025.00008 | M93: While Large Language Models (LLMs) are revolutionary, their deployment is constrained by inherent limitations such as factual hallucination and static knowledge. This survey systematically reviews Retrieval-Augmented Generation (RAG), a key paradigm for addressing these challenges by grounding LLMs in external, verifiable knowledge. To overcome the flaws of standalone models, RAG integrates LLMs with updatable knowledge bases, a hybrid approach that significantly enhances output accuracy and trustworthiness. Our primary finding is the technology's clear evolutionary trajectory, which we structure into three stages: Naive, Advanced, and Modular RAG. This progression demonstrates a shift away from monolithic parametric memory towards intelligent systems that interact with external data. By summarizing the field's progression, key challenges like retriever-generator alignment, and future directions such as integration with agentic architectures, this work concludes that RAG is a crucial technology for propelling AI to be more evidence-based and capable of complex reasoning. © 2025 IEEE.
A94: R0093 | B94: Scopus | C94: 2-s2.0-105013625460 | D94: Large language models for closed-library multi-document query, test generation, and evaluation | E94: Randolph C.; Michaleas A.; Ricke D.O. | F94: 2025 | G94: Frontiers in Artificial Intelligence | H94: Article | I94: 10.3389/frai.2025.1592013 | M94: Introduction: Learning complex, detailed, and evolving knowledge is a challenge in multiple technical professions. Relevant source knowledge is contained within many large documents and information sources with frequent updates to these documents. Knowledge tests need to be generated on new material and existing tests revised, tracking knowledge base updates. Large Language Models (LLMs) provide a framework for artificial intelligence-assisted knowledge acquisition and continued learning. Retrieval-Augmented Generation (RAG) provides a framework to leverage available, trained LLMs combined with technical area-specific knowledge bases. Methods: Herein, two methods are introduced (DaaDy: document as a dictionary and SQAD: structured question answer dictionary), which together enable effective implementation of LLM-RAG question-answering on large documents. Additionally, the AI for knowledge intensive tasks (AIKIT) solution is presented for working with numerous documents for training and continuing education. AIKIT is provided as a containerized open source solution that deploys on standalone, high performance, and cloud systems. AIKIT includes LLM, RAG, vector stores, relational database, and a Ruby on Rails web interface. Results: Coverage of source documents by LLM-RAG generated questions decreases as the length of documents increase. Segmenting source documents improve coverage of generated questions. The AIKIT solution enabled easy use of multiple LLM models with multimodal RAG source documents; AIKIT retains LLM-RAG responses for queries against one or multiple LLM models. Discussion: AIKIT provides an easy-to-use set of tools to enable users to work with complex information using LLM-RAG capabilities. AIKIT enables easy use of multiple LLM models with retention of LLM-RAG responses. Copyright © 2025 Randolph, Michaleas and Ricke.
A95: R0094 | B95: Scopus | C95: 2-s2.0-105010757173 | D95: Optimized Individual Modules in Retrieval Augmented Generation in Concrete Scenarios | E95: Gao Y. | F95: 2025 | G95: Proceedings of the 2024 4th International Symposium on Big Data and Artificial Intelligence, ISBDAI 2024 | H95: Conference paper | I95: 10.1145/3723366.3723380 | M95: As the era of big data arrives, enterprises have accumulated an increasing amount of data. How to effectively utilize cutting-edge artificial intelligence technologies to digitize massive amounts of information has become a significant challenge. Due to the exorbitant costs of training large language models (LLMs) from scratch, along with limitations such as the context window length of these models, user data privacy concerns, and model hallucinations, Retrieval-Augmented Generation (RAG) is increasingly being adopted in reality applications. In recent years, the development of large language models has led to their widespread application across industries. However, the inconsistency between the training objectives of large models and the retrieval tasks often results in severe hallucinations, particularly in very professional and personal domains, and then leads to incorrect responses. To solve this problem, RAG has been widely implemented. This paper delves into several aspects, including query augmentation, encoding combination, hybrid re-ranking, and filtering of final candidate documents, which presents a practical and effective RAG system. Extensive experiments were conducted on plant and resume datasets, with ablation studies performed for each module. Comparative analyses revealed significant improvements over existing methods, achieving an average enhancement of 4% or more in real-world applications, and a notable 6% improvement specifically in the resume dataset. The final experimental analysis substantiates the efficacy of this approach. © 2024 Copyright held by the owner/author(s).
A96: R0095 | B96: Scopus | C96: 2-s2.0-105033142921 | D96: A Comprehensive Study-Retrieval-Augmented Generation(RAG) | E96: Kiruba S.; Sam Anish C.; Krishna R.S.B.; Rayen S.J. | F96: 2025 | G96: Proceedings - IEEE 10th International Conference on Smart Structures and Systems, ICSSS 2025 | H96: Conference paper | I96: 10.1109/icsss66939.2025.11346240 | M96: Retrieval-Augmented Generation (RAG) which represents a substantial new approach from large language model (LLM) technology by including external, up-to-date knowledge sources as part of the generation process. The hybrid model addresses critical limitations of the LLMs based on simply containing static training data, hallucinations, and a lack of full transparency, by providing the model with pertinent knowledge from dynamic databases or documents to complement the model. The work provides an extensive review of RAG architectures and their core components-retrieval, generation, and augmentation-along with their integration to enhance factual accuracy and contextual relevance. Finally, we discuss the recent technological advancements, different applications in knowledge-intensive task domains, and sustainability of continuous knowledge sources without retraining costs. We also highlight existing barriers such as efficient retrieval and evaluation, and opportunities for future research directions to continue the advancement of RAG systems. By supplanting the static nature of AI knowledge with real-time retrieval of information; RAG opens a new way in which durable, scalable, and domain-adaptive content can be generated by AI. © 2025 IEEE.
A97: R0096 | B97: Scopus | C97: 2-s2.0-105034205619 | D97: A Survey on Retrieval-Augmented Generation (RAG) Models: Recent Advances and Challenges | E97: Bhanushali V.; Dash A.; Bhavsar T.; Hundare V.; Patil P. | F97: 2025 | G97: 16th International Conference on Advances in Computing, Control, and Telecommunication Technologies, ACT 2025 | H97: Conference paper | M97: The combination of retrieval systems with large language models (LLMs) in Retrieval-Augmented Generation (RAG) models has greatly increased natural language processing by enhancing factual correctness and context in generated responses. RAG models include outside knowledge sources to underpin their outputs, unlike standard LLMs that may generate false or misleading information. This makes them extremely useful for jobs like summarizing and answering questions that call for exact information. © Grenze Scientific Society, 2025.
A98: R0097 | B98: Scopus | C98: 2-s2.0-105032685891 | D98: Nyaya Sathi: A BNS-Aware Legal Assistant | E98: Dixit A.; Jain V.; Yadav S.; Tiwari V.; Awasthi S.; Trivedi P.; Choudhury T. | F98: 2025 | G98: 2025 International Conference on Computational Intelligence and Knowledge Economy, ICCIKE 2025 | H98: Conference paper | I98: 10.1109/iccike67021.2025.11318190 | M98: The recent enhancements in the domain of Generative A I have opened new options for intelligent legal reasoning, legal context-aware retrieval, and document drafting automation through Retrieval-Augmented Generation (RAG). However, Large Language Models (LLMs) often face challenges such as hallucinations and lack of domain-specific knowledge. This paper presents a RAG-based architecture tailored for the legal domain. Nyaya-Sathi is an AI-powered assistant for generating contextaware legal responses which is based on the recent legal system of India called Bharatiya Nyaya Sanhita (BNS). The system combines semantic retrieval using ChromaDB with structured text generation using the Grok API. This is specifically designed to handle the BNS-compliant queries with its reasoning. Implementation on various models demonstrates how the legal data can be preprocessed and embedded into a vector database, andcan support reliable retrieval and reduce hallucination rates. The evaluation on various datasets show significant improvements in accuracy, contextual relevance, and overall reliability. © 2025 IEEE.
A99: R0098 | B99: Scopus | C99: 2-s2.0-85177620561 | D99: RRAML: Reinforced Retrieval Augmented Machine Learning | E99: Bacciu A.; Cuconasu F.; Siciliano F.; Silvestri F.; Tonellotto N.; Trappolini G. | F99: 2023 | G99: CEUR Workshop Proceedings | H99: Conference paper | M99: The emergence of large language models (LLMs) has revolutionized machine learning and related fields, showcasing remarkable abilities in comprehending, generating, and manipulating human language. However, their conventional usage through API-based text prompt submissions imposes certain limitations in terms of context constraints and external source availability. LLMs suffer from the problem of hallucinating text, and in the last year, several approaches have been devised to overcome this issue: adding an external Knowledge Base or an external memory consisting of embeddings stored and retrieved by vector databases. In all the current approaches, though, the main issues are: (i) they need to access an embedding model and then adapt it to the task they have to solve; (ii) in case they have to optimize the embedding model, they need to have access to the parameters of the LLM, which in many cases are “black boxes”. To address these challenges, we propose a novel framework called Reinforced Retrieval Augmented Machine Learning (RRAML). RRAML integrates the reasoning capabilities of LLMs with supporting information retrieved by a purpose-built retriever from a vast user-provided database. By leveraging recent advancements in reinforcement learning, our method effectively addresses several critical challenges. Firstly, it circumvents the need for accessing LLM gradients. Secondly, our method alleviates the burden of retraining LLMs for specific tasks, as it is often impractical or impossible due to restricted access to the model and the computational intensity involved. Additionally, we seamlessly link the retriever’s task with the reasoner, mitigating hallucinations and reducing irrelevant and potentially damaging retrieved documents. We believe that the research agenda outlined in this paper has the potential to profoundly impact the field of AI, democratizing access to and utilization of LLMs for a wide range of entities. © 2023 Copyright for this paper by its authors.
A100: R0099 | B100: Scopus | C100: 2-s2.0-105033019795 | D100: Unlocking LLM Potential: Critical Breakthroughs and Frontier Explorations in Retrieval-Augmented Generation | E100: Liu Y.; Wang Z.; Chen Y.; He Y.; Lian J.; Lu H. | F100: 2025 | G100: Proceedings - 2025 IEEE 10th International Conference on Data Science in Cyberspace, DSC 2025 | H100: Conference paper | I100: 10.1109/dsc67331.2025.00010 | M100: The pervasive challenge of Large Language Models (LLMs) hallucinating and relying on static knowledge has spurred a critical evolution in AI: Retrieval-Augmented Generation (RAG). This transformative paradigm integrates external information retrieval with LLM generation, significantly enhancing factual accuracy, timeliness, and domain specificity. RAG transforms LLMs into dynamic, verifiable systems. This paper comprehensively surveys RAG's core principles, architectural advancements, challenges, and future directions, including multimodal and agentic RAG, providing a foundational understanding of its immense potential in developing more reliable and adaptive AI. © 2025 IEEE.
